{"id":"CHEMBL332750","indications":[{"disease":"EFO_0000384","efoName":"crohn's disease","references":[{"source":"ClinicalTrials","ids":["NCT00317369","NCT00989573"]}],"maxPhaseForIndication":2},{"disease":"EFO_0000341","efoName":"chronic obstructive pulmonary disease","references":[{"source":"ClinicalTrials","ids":["NCT00874497","NCT00917150"]}],"maxPhaseForIndication":2},{"disease":"EFO_0000729","efoName":"ulcerative colitis","references":[{"source":"ClinicalTrials","ids":["NCT00064441","NCT00064454","NCT00092508","NCT00317356"]}],"maxPhaseForIndication":3}],"approvedIndications":[],"indicationCount":3}
{"id":"CHEMBL373742","indications":[{"disease":"EFO_0006834","efoName":"septic shock","references":[{"source":"ClinicalTrials","ids":["NCT00269685","NCT00481572","NCT01718613"]}],"maxPhaseForIndication":3},{"disease":"EFO_0009492","efoName":"cardiac arrest","references":[{"source":"ClinicalTrials","ids":["NCT00358579","NCT00628550","NCT00729794"]}],"maxPhaseForIndication":3},{"disease":"EFO_0004278","efoName":"sudden cardiac arrest","references":[{"source":"ClinicalTrials","ids":["NCT00411879","NCT03640949"]}],"maxPhaseForIndication":2},{"disease":"EFO_0005207","efoName":"congenital heart disease","references":[{"source":"ClinicalTrials","ids":["NCT03088345"]}],"maxPhaseForIndication":2},{"disease":"EFO_0009637","efoName":"pleural effusion","references":[{"source":"ClinicalTrials","ids":["NCT02975999"]}],"maxPhaseForIndication":2},{"disease":"EFO_0003758","efoName":"autism","references":[{"source":"ClinicalTrials","ids":["NCT03204786"]}],"maxPhaseForIndication":2},{"disease":"EFO_0003843","efoName":"pain","references":[{"source":"ClinicalTrials","ids":["NCT03446456"]}],"maxPhaseForIndication":1},{"disease":"MONDO_0003061","efoName":"benign muscle neoplasm","references":[{"source":"ClinicalTrials","ids":["NCT01861015"]}],"maxPhaseForIndication":3},{"disease":"MONDO_0001572","efoName":"leiomyoma","references":[{"source":"ClinicalTrials","ids":["NCT03930069"]}],"maxPhaseForIndication":2},{"disease":"EFO_0004610","efoName":"acute lung injury","references":[{"source":"ClinicalTrials","ids":["NCT00624650"]}],"maxPhaseForIndication":2},{"disease":"EFO_0005251","efoName":"hypotension","references":[{"source":"ClinicalTrials","ids":["NCT04463394"]}],"maxPhaseForIndication":0},{"disease":"MONDO_0002009","efoName":"major depressive disorder","references":[{"source":"ClinicalTrials","ids":["NCT01606384"]}],"maxPhaseForIndication":2},{"disease":"HP_0031273","efoName":"shock","references":[{"source":"ClinicalTrials","ids":["NCT00420407","NCT01505231","NCT01611935","NCT03483753"]}],"maxPhaseForIndication":3},{"disease":"MONDO_0004782","efoName":"diabetes insipidus","references":[{"source":"DailyMed","ids":["40dab227-b05b-4e72-a59c-6e6f8a80252e","1b316ff5-b7f8-4509-acc4-fd263d0a1703","af7b1a71-bc6d-42df-93b3-14be5d3eeb33","bd6a0d6e-562a-4364-81a5-c609f3936327","fa461271-91e8-4a83-8435-5f52040ab41b","5d6cdb9f-f9cd-488e-8c88-bec8606aa4cf"]}],"maxPhaseForIndication":4},{"disease":"EFO_0003756","efoName":"autism spectrum disorder","references":[{"source":"ClinicalTrials","ids":["NCT01962870"]}],"maxPhaseForIndication":2},{"disease":"EFO_0003777","efoName":"heart disease","references":[{"source":"ClinicalTrials","ids":["NCT04501861"]}],"maxPhaseForIndication":3},{"disease":"MONDO_0005149","efoName":"pulmonary hypertension","references":[{"source":"ClinicalTrials","ids":["NCT01370096"]}],"maxPhaseForIndication":2},{"disease":"HP_0100806","efoName":"sepsis","references":[{"source":"DailyMed","ids":["b1147beb-743e-4c62-8927-91192447f8b8"]}],"maxPhaseForIndication":4}],"approvedIndications":["HP_0100806","MONDO_0004782"],"indicationCount":18}
{"id":"CHEMBL2109467","indications":[{"disease":"EFO_0000676","efoName":"psoriasis","references":[{"source":"ClinicalTrials","ids":["NCT00443326"]}],"maxPhaseForIndication":2},{"disease":"EFO_0001060","efoName":"celiac disease","references":[{"source":"ClinicalTrials","ids":["NCT02637141","NCT04424927"]}],"maxPhaseForIndication":2},{"disease":"EFO_0004208","efoName":"vitiligo","references":[{"source":"ClinicalTrials","ids":["NCT04338581"]}],"maxPhaseForIndication":2},{"disease":"EFO_0000685","efoName":"rheumatoid arthritis","references":[{"source":"ClinicalTrials","ids":["NCT00433875"]}],"maxPhaseForIndication":2}],"approvedIndications":[],"indicationCount":4}
{"id":"CHEMBL1201118","indications":[{"disease":"EFO_0003102","efoName":"osteomyelitis","references":[{"source":"ClinicalTrials","ids":["NCT02099240"]}],"maxPhaseForIndication":0}],"approvedIndications":[],"indicationCount":1}
{"id":"CHEMBL59","indications":[{"disease":"EFO_0003917","efoName":"premature birth","references":[{"source":"ClinicalTrials","ids":["NCT04525495"]}],"maxPhaseForIndication":2},{"disease":"MONDO_0002050","efoName":"depressive disorder","references":[{"source":"ClinicalTrials","ids":["NCT01153802"]}],"maxPhaseForIndication":1},{"disease":"EFO_0000373","efoName":"congestive heart failure","references":[{"source":"DailyMed","ids":["763d2b07-9cea-782e-e053-2a91aa0adc01"]}],"maxPhaseForIndication":4},{"disease":"EFO_0006834","efoName":"septic shock","references":[{"source":"ClinicalTrials","ids":["NCT00604019"]}],"maxPhaseForIndication":3},{"disease":"EFO_1002048","efoName":"kidney failure","references":[{"source":"DailyMed","ids":["763d2b07-9cea-782e-e053-2a91aa0adc01","7896052c-2a72-ca89-e053-2a91aa0ae86e"]}],"maxPhaseForIndication":4},{"disease":"EFO_0000400","efoName":"diabetes mellitus","references":[{"source":"ClinicalTrials","ids":["NCT02706977"]}],"maxPhaseForIndication":1},{"disease":"EFO_0003144","efoName":"heart failure","references":[{"source":"ClinicalTrials","ids":["NCT00953303","NCT01132846"]}],"maxPhaseForIndication":2},{"disease":"EFO_0000612","efoName":"myocardial infarction","references":[{"source":"DailyMed","ids":["763d2b07-9cea-782e-e053-2a91aa0adc01","7896052c-2a72-ca89-e053-2a91aa0ae86e"]}],"maxPhaseForIndication":4},{"disease":"HP_0031273","efoName":"shock","references":[{"source":"ClinicalTrials","ids":["NCT00314704"]}],"maxPhaseForIndication":3},{"disease":"MONDO_0005180","efoName":"parkinson disease","references":[{"source":"ClinicalTrials","ids":["NCT00139867","NCT00139880","NCT00465452","NCT00562198","NCT01039090","NCT01515410","NCT02347059","NCT02763839","NCT04332276"]}],"maxPhaseForIndication":3},{"disease":"EFO_0000319","efoName":"cardiovascular disease","references":[{"source":"ATC","ids":["C01CA04"]}],"maxPhaseForIndication":4},{"disease":"MONDO_0005180","efoName":"parkinson disease","references":[{"source":"ClinicalTrials","ids":["NCT01039090"]}],"maxPhaseForIndication":3},{"disease":"HP_0100543","efoName":"cognitive impairment","references":[{"source":"ClinicalTrials","ids":["NCT02428062"]}],"maxPhaseForIndication":2},{"disease":"EFO_0005207","efoName":"congenital heart disease","references":[{"source":"ClinicalTrials","ids":["NCT04536194"]}],"maxPhaseForIndication":3}],"approvedIndications":["EFO_0000373","EFO_0000319","EFO_0000612","EFO_1002048"],"indicationCount":14}
{"id":"CHEMBL4297862","indications":[{"disease":"EFO_1000781","efoName":"overactive bladder","references":[{"source":"ClinicalTrials","ids":["NCT04113941"]},{"source":"DailyMed","ids":["33d066a9-34ff-4a1a-b38b-d10983df3300"]}],"maxPhaseForIndication":4},{"disease":"EFO_1000999","efoName":"joint disease","references":[{"source":"ClinicalTrials","ids":["NCT03726788"]}],"maxPhaseForIndication":2},{"disease":"HP_0000975","efoName":"hyperhidrosis","references":[{"source":"ClinicalTrials","ids":["NCT01262339","NCT01799824"]}],"maxPhaseForIndication":2},{"disease":"MONDO_0005277","efoName":"migraine disorder","references":[{"source":"DailyMed","ids":["33d066a9-34ff-4a1a-b38b-d10983df3300"]}],"maxPhaseForIndication":4},{"disease":"Orphanet_93955","efoName":"benign essential blepharospasm","references":[{"source":"ClinicalTrials","ids":["NCT03216473"]}],"maxPhaseForIndication":3},{"disease":"HP_0000473","efoName":"torticollis","references":[{"source":"ClinicalTrials","ids":["NCT03805152"]}],"maxPhaseForIndication":3},{"disease":"EFO_0009846","efoName":"muscle cramp","references":[{"source":"ClinicalTrials","ids":["NCT04589364"]}],"maxPhaseForIndication":3},{"disease":"EFO_0006865","efoName":"urgency urinary incontinence","references":[{"source":"DailyMed","ids":["33d066a9-34ff-4a1a-b38b-d10983df3300"]}],"maxPhaseForIndication":4}],"approvedIndications":["MONDO_0005277","EFO_0006865","EFO_1000781"],"indicationCount":8}
{"id":"CHEMBL53","indications":[{"disease":"MONDO_0005180","efoName":"parkinson disease","references":[{"source":"DailyMed","ids":["3235535d-9ef9-4657-8b2a-176a807d091c","558399d2-96c6-4bc5-9d44-93b102e4189a"]},{"source":"ClinicalTrials","ids":["NCT00142545","NCT00145171","NCT00200512","NCT00200525","NCT00610103","NCT00955318","NCT01058291","NCT01063621","NCT01770145","NCT02006121","NCT02549573","NCT03292016"]}],"maxPhaseForIndication":4},{"disease":"EFO_0000616","efoName":"neoplasm","references":[{"source":"ClinicalTrials","ids":["NCT00003822","NCT00004049"]}],"maxPhaseForIndication":1},{"disease":"EFO_0004234","efoName":"erectile dysfunction","references":[{"source":"ATC","ids":["G04BE07"]}],"maxPhaseForIndication":4},{"disease":"HP_0000738","efoName":"hallucinations","references":[{"source":"ClinicalTrials","ids":["NCT02702076"]}],"maxPhaseForIndication":2},{"disease":"EFO_0003882","efoName":"osteoporosis","references":[{"source":"ClinicalTrials","ids":["NCT00078026"]}],"maxPhaseForIndication":1},{"disease":"MONDO_0043510","efoName":"brain injury","references":[{"source":"ClinicalTrials","ids":["NCT00761228"]}],"maxPhaseForIndication":2},{"disease":"MONDO_0007079","efoName":"alcohol dependence","references":[{"source":"ClinicalTrials","ids":["NCT00437177"]}],"maxPhaseForIndication":2},{"disease":"MONDO_0005180","efoName":"parkinson disease","references":[{"source":"ClinicalTrials","ids":["NCT00040209","NCT00346827","NCT00472355","NCT00758368","NCT01039090","NCT01504178","NCT01683292","NCT02228590","NCT02339064","NCT02469090","NCT02542696","NCT02688465","NCT02702076","NCT02864004","NCT02940912","NCT03187301","NCT03292016","NCT03391882","NCT04879134","NCT04887467"]},{"source":"ATC","ids":["N04BC07"]}],"maxPhaseForIndication":4}],"approvedIndications":["MONDO_0005180","EFO_0004234"],"indicationCount":8}
{"id":"CHEMBL566","indications":[{"disease":"MONDO_0001056","efoName":"gastric cancer","references":[{"source":"ClinicalTrials","ids":["NCT00152243"]}],"maxPhaseForIndication":3},{"disease":"EFO_0003869","efoName":"breast neoplasm","references":[{"source":"ClinicalTrials","ids":["NCT01262274"]}],"maxPhaseForIndication":3},{"disease":"MONDO_0001187","efoName":"urinary bladder cancer","references":[{"source":"ClinicalTrials","ids":["NCT01082510"]}],"maxPhaseForIndication":3},{"disease":"EFO_0000199","efoName":"oral squamous cell carcinoma","references":[{"source":"ClinicalTrials","ids":["NCT03121313"]}],"maxPhaseForIndication":2},{"disease":"EFO_0006859","efoName":"head and neck malignant neoplasia","references":[{"source":"ClinicalTrials","ids":["NCT00336947","NCT00855881"]}],"maxPhaseForIndication":3},{"disease":"EFO_1001951","efoName":"colorectal carcinoma","references":[{"source":"ClinicalTrials","ids":["NCT00002801","NCT00004860","NCT00152230","NCT00378716","NCT00385970","NCT00660894","NCT00905047"]}],"maxPhaseForIndication":3},{"disease":"EFO_1000657","efoName":"rectum cancer","references":[{"source":"ClinicalTrials","ids":["NCT00207831"]}],"maxPhaseForIndication":3},{"disease":"MONDO_0007254","efoName":"breast cancer","references":[{"source":"ClinicalTrials","ids":["NCT00005608","NCT00152178","NCT00152191"]}],"maxPhaseForIndication":3},{"disease":"EFO_0003060","efoName":"non-small cell lung carcinoma","references":[{"source":"ClinicalTrials","ids":["NCT01037998"]}],"maxPhaseForIndication":2},{"disease":"EFO_0000311","efoName":"cancer","references":[{"source":"ClinicalTrials","ids":["NCT00705874"]}],"maxPhaseForIndication":1},{"disease":"EFO_0000616","efoName":"neoplasm","references":[{"source":"ClinicalTrials","ids":["NCT00003925","NCT00009815","NCT00009828"]}],"maxPhaseForIndication":1},{"disease":"MONDO_0021355","efoName":"neoplasm of esophagus","references":[{"source":"ClinicalTrials","ids":["NCT00037089"]}],"maxPhaseForIndication":2},{"disease":"EFO_0000182","efoName":"hepatocellular carcinoma","references":[{"source":"ClinicalTrials","ids":["NCT00384800","NCT00519688","NCT01539018","NCT02447679"]}],"maxPhaseForIndication":2}],"approvedIndications":[],"indicationCount":13}
{"id":"CHEMBL657","indications":[{"disease":"EFO_1000783","efoName":"diabetic neuropathy","references":[{"source":"ClinicalTrials","ids":["NCT00837941"]}],"maxPhaseForIndication":2},{"disease":"HP_0012735","efoName":"cough","references":[{"source":"DailyMed","ids":["d18e22f2-8cda-4862-b437-e83648a5108a","0402876e-1695-4daf-8ab7-f6d99b1ac821","20a67ffb-601a-417b-a0ea-16132abfdc92","058b2021-8a61-40b0-8a2e-a784d2b847fb","0c5ab61b-0b04-4a39-a0c2-5b39432833a1","2da2ab5b-35bf-413b-96ef-6bcdf4a85916","a7847413-e556-4f88-8a7f-a8528afbe927","aea32721-a164-4eed-8eb6-f91a1ced20ef","98e8e0d7-1bff-6aa8-e053-2995a90a060d","51f8b2a9-e635-4be7-9c3b-1a7fab106d77","1d26a227-4d73-44ec-b79c-9b0f02da5691","994e0736-6b07-43ae-bc4e-575f61166c80","d5ebda54-8917-4bd7-af47-354432f13cc8","dea43184-d5c1-4b69-aabf-7d4315e0a8b5","35e3d154-f914-426d-a702-328cbc27ceba","b747cb49-e11b-4dca-90a3-2510b430880b","0163af5d-5256-404e-9195-624c4ffc8087","01bf4051-3a70-4eaf-92cc-49db854d50a0","55762d52-a35b-4087-b133-a9f446f64f7f","7decc168-e847-4bbe-910b-26081469406f","739aedfd-d5b8-4be8-9453-c7229ec79e26"]}],"maxPhaseForIndication":4},{"disease":"MONDO_0011962","efoName":"endometrial cancer","references":[{"source":"ClinicalTrials","ids":["NCT00515073"]}],"maxPhaseForIndication":2},{"disease":"EFO_0006928","efoName":"motion sickness","references":[{"source":"DailyMed","ids":["bc71539e-1a33-4709-8a24-c2894e8dbc1c","4fe466c4-2dd9-42cd-8db8-761f9194d102","a45fd02d-f558-4116-ad97-0583f92dc8e9","82cd7a3c-acd6-44dc-8c95-f066162a510c","056b6032-c92d-458e-97d4-a964d1adb38a","0998947c-cfba-497e-bf7a-9c7f8fff1764"]}],"maxPhaseForIndication":4},{"disease":"MONDO_0002050","efoName":"depressive disorder","references":[{"source":"ClinicalTrials","ids":["NCT02106325","NCT02374567"]}],"maxPhaseForIndication":3},{"disease":"EFO_0005952","efoName":"non-hodgkins lymphoma","references":[{"source":"ClinicalTrials","ids":["NCT00324467"]}],"maxPhaseForIndication":2},{"disease":"Orphanet_60","efoName":"alpha-1-antitrypsin deficiency","references":[{"source":"ClinicalTrials","ids":["NCT02363946"]}],"maxPhaseForIndication":1},{"disease":"EFO_0008521","efoName":"rhinitis","references":[{"source":"ClinicalTrials","ids":["NCT01177852"]}],"maxPhaseForIndication":3},{"disease":"EFO_0002690","efoName":"systemic lupus erythematosus","references":[{"source":"ClinicalTrials","ids":["NCT04963296"]}],"maxPhaseForIndication":3},{"disease":"EFO_0007359","efoName":"mast-cell leukemia","references":[{"source":"ClinicalTrials","ids":["NCT00186628"]}],"maxPhaseForIndication":2},{"disease":"EFO_0001378","efoName":"multiple myeloma","references":[{"source":"ClinicalTrials","ids":["NCT00899847","NCT01985126","NCT01998971","NCT03319667","NCT04268498"]}],"maxPhaseForIndication":3},{"disease":"EFO_0000220","efoName":"acute lymphoblastic leukemia","references":[{"source":"ClinicalTrials","ids":["NCT03913559"]}],"maxPhaseForIndication":2},{"disease":"EFO_0000096","efoName":"neoplasm of mature b-cells","references":[{"source":"ClinicalTrials","ids":["NCT00324467"]}],"maxPhaseForIndication":2},{"disease":"EFO_0000222","efoName":"acute myeloid leukemia","references":[{"source":"ClinicalTrials","ids":["NCT04580121"]}],"maxPhaseForIndication":1},{"disease":"EFO_0000311","efoName":"cancer","references":[{"source":"ClinicalTrials","ids":["NCT01017731"]}],"maxPhaseForIndication":2},{"disease":"MONDO_0044917","efoName":"t-lymphoblastic lymphoma","references":[{"source":"ClinicalTrials","ids":["NCT02999633"]}],"maxPhaseForIndication":2},{"disease":"EFO_1001264","efoName":"anemia, hemolytic, autoimmune","references":[{"source":"ClinicalTrials","ids":["NCT04661033"]}],"maxPhaseForIndication":1},{"disease":"MONDO_0007254","efoName":"breast cancer","references":[{"source":"ClinicalTrials","ids":["NCT01332630"]}],"maxPhaseForIndication":2},{"disease":"EFO_0000403","efoName":"diffuse large b-cell lymphoma","references":[{"source":"ClinicalTrials","ids":["NCT04660799"]}],"maxPhaseForIndication":2},{"disease":"EFO_0004239","efoName":"chronic hepatitis b virus infection","references":[{"source":"ClinicalTrials","ids":["NCT02452528"]}],"maxPhaseForIndication":2},{"disease":"MONDO_0008315","efoName":"prostate cancer","references":[{"source":"ClinicalTrials","ids":["NCT00887640"]}],"maxPhaseForIndication":2},{"disease":"HP_0002315","efoName":"headache","references":[{"source":"ClinicalTrials","ids":["NCT03081416"]}],"maxPhaseForIndication":3},{"disease":"EFO_0002610","efoName":"cocaine dependence","references":[{"source":"ClinicalTrials","ids":["NCT02037126"]}],"maxPhaseForIndication":2},{"disease":"MONDO_0002009","efoName":"major depressive disorder","references":[{"source":"ClinicalTrials","ids":["NCT02476058"]}],"maxPhaseForIndication":1},{"disease":"Orphanet_365","efoName":"glycogen storage disease due to acid maltase deficiency","references":[{"source":"ClinicalTrials","ids":["NCT02240407"]}],"maxPhaseForIndication":1},{"disease":"EFO_0003843","efoName":"pain","references":[{"source":"ClinicalTrials","ids":["NCT02229539"]}],"maxPhaseForIndication":3},{"disease":"HP_0000989","efoName":"pruritus","references":[{"source":"ATC","ids":["D04AA32"]}],"maxPhaseForIndication":4},{"disease":"EFO_1001904","efoName":"oral mucositis","references":[{"source":"ClinicalTrials","ids":["NCT02229539"]}],"maxPhaseForIndication":3},{"disease":"MONDO_0017287","efoName":"igg4-related disease","references":[{"source":"ClinicalTrials","ids":["NCT04918147"]}],"maxPhaseForIndication":2},{"disease":"EFO_0000095","efoName":"chronic lymphocytic leukemia","references":[{"source":"ClinicalTrials","ids":["NCT00840853"]}],"maxPhaseForIndication":1},{"disease":"MONDO_0005271","efoName":"allergic disease","references":[{"source":"ATC","ids":["R06AA52","R06AA02"]}],"maxPhaseForIndication":4},{"disease":"EFO_0000574","efoName":"lymphoma","references":[{"source":"ClinicalTrials","ids":["NCT00490009"]}],"maxPhaseForIndication":2},{"disease":"HP_0000726","efoName":"dementia","references":[{"source":"ClinicalTrials","ids":["NCT02374567"]}],"maxPhaseForIndication":3},{"disease":"EFO_0003843","efoName":"pain","references":[{"source":"ClinicalTrials","ids":["NCT03396250"]}],"maxPhaseForIndication":1},{"disease":"MONDO_0005277","efoName":"migraine disorder","references":[{"source":"ClinicalTrials","ids":["NCT00682734"]}],"maxPhaseForIndication":3},{"disease":"EFO_1000657","efoName":"rectum cancer","references":[{"source":"ClinicalTrials","ids":["NCT00226941"]}],"maxPhaseForIndication":1},{"disease":"EFO_0005854","efoName":"allergic rhinitis","references":[{"source":"ClinicalTrials","ids":["NCT00762749"]}],"maxPhaseForIndication":1},{"disease":"EFO_0000540","efoName":"immune system disease","references":[{"source":"ClinicalTrials","ids":["NCT04294459"]}],"maxPhaseForIndication":1},{"disease":"EFO_0003060","efoName":"non-small cell lung carcinoma","references":[{"source":"ClinicalTrials","ids":["NCT04165096"]}],"maxPhaseForIndication":2},{"disease":"EFO_0000384","efoName":"crohn's disease","references":[{"source":"ClinicalTrials","ids":["NCT04224558"]}],"maxPhaseForIndication":1},{"disease":"MONDO_0004658","efoName":"breast carcinoma in situ","references":[{"source":"ClinicalTrials","ids":["NCT04862585"]}],"maxPhaseForIndication":2},{"disease":"EFO_0004698","efoName":"insomnia","references":[{"source":"DailyMed","ids":["91e5bd4a-b981-5b26-e053-2a95a90af9fe","335490a4-9e74-455e-b365-d74d7bc3a588","05ec6e7f-d73f-4be3-9ee3-4957898ba210","16547905-59c0-4936-82e1-2d9f5935d8dd"]}],"maxPhaseForIndication":4},{"disease":"MONDO_0005271","efoName":"allergic disease","references":[{"source":"ClinicalTrials","ids":["NCT01978483"]}],"maxPhaseForIndication":1},{"disease":"HP_0000989","efoName":"pruritus","references":[{"source":"DailyMed","ids":["bfa57f40-a1f4-4b53-95d5-1d6d6ed0233f","6f68cbbb-6269-4bb3-8cc9-50b146703b42","18998e1c-1254-4d0c-93f1-26652c5ca076","4f4c801b-d894-4fa3-b024-6ca41a5f2a95","5b4add17-6c3d-4093-826a-2edb41c1d1db"]}],"maxPhaseForIndication":4},{"disease":"EFO_0006890","efoName":"fibrosis","references":[{"source":"ClinicalTrials","ids":["NCT03142165"]}],"maxPhaseForIndication":1},{"disease":"HP_0001742","efoName":"nasal congestion","references":[{"source":"DailyMed","ids":["57d23d57-2e55-4c2d-ad09-f523afc62e13","c66b6d3e-7426-4858-8291-413bab9ca0de","17a39de8-1702-0711-e054-00144ff8d46c","079de233-aacb-47d3-90fe-d66f1ca7bb15","20a67ffb-601a-417b-a0ea-16132abfdc92","058b2021-8a61-40b0-8a2e-a784d2b847fb","0c5ab61b-0b04-4a39-a0c2-5b39432833a1","2da2ab5b-35bf-413b-96ef-6bcdf4a85916","0ae329f7-d059-47d2-8e43-05c569e134d1","a7847413-e556-4f88-8a7f-a8528afbe927","7abace52-4d9c-429b-b9a9-96d06261ef50","09bb548f-f833-4eec-bacc-e4f1e71f5cf2","aea32721-a164-4eed-8eb6-f91a1ced20ef","98e8e0d7-1bff-6aa8-e053-2995a90a060d","51f8b2a9-e635-4be7-9c3b-1a7fab106d77","994e0736-6b07-43ae-bc4e-575f61166c80","bd5d362e-095f-42f3-8df9-086220182b4d","dea43184-d5c1-4b69-aabf-7d4315e0a8b5","35e3d154-f914-426d-a702-328cbc27ceba","b747cb49-e11b-4dca-90a3-2510b430880b","0163af5d-5256-404e-9195-624c4ffc8087","01bf4051-3a70-4eaf-92cc-49db854d50a0","55762d52-a35b-4087-b133-a9f446f64f7f","7b4b309b-3726-4a14-b7e6-64469b994322","3893f772-6168-4e51-9eb5-e73989547a9a"]}],"maxPhaseForIndication":4},{"disease":"HP_0002018","efoName":"nausea","references":[{"source":"ClinicalTrials","ids":["NCT00475306"]},{"source":"DailyMed","ids":["bc71539e-1a33-4709-8a24-c2894e8dbc1c","056b6032-c92d-458e-97d4-a964d1adb38a","0998947c-cfba-497e-bf7a-9c7f8fff1764"]}],"maxPhaseForIndication":4},{"disease":"EFO_0005252","efoName":"orthostatic hypotension","references":[{"source":"ClinicalTrials","ids":["NCT00223691"]}],"maxPhaseForIndication":1},{"disease":"MONDO_0002367","efoName":"kidney cancer","references":[{"source":"ClinicalTrials","ids":["NCT01392183"]}],"maxPhaseForIndication":2},{"disease":"EFO_0000681","efoName":"renal cell carcinoma","references":[{"source":"ClinicalTrials","ids":["NCT00030992"]}],"maxPhaseForIndication":2},{"disease":"EFO_0007214","efoName":"common cold","references":[{"source":"DailyMed","ids":["3893f772-6168-4e51-9eb5-e73989547a9a","c66b6d3e-7426-4858-8291-413bab9ca0de","0402876e-1695-4daf-8ab7-f6d99b1ac821","17a39de8-1702-0711-e054-00144ff8d46c","079de233-aacb-47d3-90fe-d66f1ca7bb15","058b2021-8a61-40b0-8a2e-a784d2b847fb","0c5ab61b-0b04-4a39-a0c2-5b39432833a1","2da2ab5b-35bf-413b-96ef-6bcdf4a85916","0ae329f7-d059-47d2-8e43-05c569e134d1","82771f6a-8b3d-4ffa-8b35-09c2faf3582c","09bb548f-f833-4eec-bacc-e4f1e71f5cf2","be2207b7-b8f8-7fba-e053-2a95a90abd16","abc0e348-8532-4658-bd8c-d7dbe5a28c7d","b52fc311-8853-4116-941b-8be35456abba","b747cb49-e11b-4dca-90a3-2510b430880b","7b4b309b-3726-4a14-b7e6-64469b994322","739aedfd-d5b8-4be8-9453-c7229ec79e26","57d23d57-2e55-4c2d-ad09-f523afc62e13"]}],"maxPhaseForIndication":4},{"disease":"EFO_0004270","efoName":"restless legs syndrome","references":[{"source":"ClinicalTrials","ids":["NCT01332318","NCT01411124"]}],"maxPhaseForIndication":2},{"disease":"EFO_0009516","efoName":"burn","references":[{"source":"DailyMed","ids":["18998e1c-1254-4d0c-93f1-26652c5ca076","4f4c801b-d894-4fa3-b024-6ca41a5f2a95"]}],"maxPhaseForIndication":4},{"disease":"EFO_0003956","efoName":"seasonal allergic rhinitis","references":[{"source":"DailyMed","ids":["c66b6d3e-7426-4858-8291-413bab9ca0de","0402876e-1695-4daf-8ab7-f6d99b1ac821","079de233-aacb-47d3-90fe-d66f1ca7bb15","20a67ffb-601a-417b-a0ea-16132abfdc92","058b2021-8a61-40b0-8a2e-a784d2b847fb","0c5ab61b-0b04-4a39-a0c2-5b39432833a1","82771f6a-8b3d-4ffa-8b35-09c2faf3582c","0ae329f7-d059-47d2-8e43-05c569e134d1","a7847413-e556-4f88-8a7f-a8528afbe927","7abace52-4d9c-429b-b9a9-96d06261ef50","09bb548f-f833-4eec-bacc-e4f1e71f5cf2","aea32721-a164-4eed-8eb6-f91a1ced20ef","be2207b7-b8f8-7fba-e053-2a95a90abd16","1d26a227-4d73-44ec-b79c-9b0f02da5691","abc0e348-8532-4658-bd8c-d7dbe5a28c7d","b52fc311-8853-4116-941b-8be35456abba","1f3a4082-78a3-468b-bd38-f2e64ac84f6b","35e3d154-f914-426d-a702-328cbc27ceba","b747cb49-e11b-4dca-90a3-2510b430880b","d2d07121-66f2-4726-acd5-6e8c33d91024","0163af5d-5256-404e-9195-624c4ffc8087","7decc168-e847-4bbe-910b-26081469406f","0f0b5330-7e97-489f-a0c7-54f68f6675ce","739aedfd-d5b8-4be8-9453-c7229ec79e26","3893f772-6168-4e51-9eb5-e73989547a9a"]}],"maxPhaseForIndication":4},{"disease":"HP_0002017","efoName":"nausea and vomiting","references":[{"source":"DailyMed","ids":["0998947c-cfba-497e-bf7a-9c7f8fff1764"]}],"maxPhaseForIndication":4},{"disease":"MP_0001845","efoName":"inflammation","references":[{"source":"ClinicalTrials","ids":["NCT01177852"]}],"maxPhaseForIndication":3},{"disease":"EFO_0009688","efoName":"stomatitis","references":[{"source":"ClinicalTrials","ids":["NCT01837446"]}],"maxPhaseForIndication":3},{"disease":"EFO_0003958","efoName":"sunburn","references":[{"source":"DailyMed","ids":["bfa57f40-a1f4-4b53-95d5-1d6d6ed0233f","37fe6d82-adee-4f58-e054-00144ff88e88","18998e1c-1254-4d0c-93f1-26652c5ca076"]}],"maxPhaseForIndication":4},{"disease":"EFO_0000403","efoName":"diffuse large b-cell lymphoma","references":[{"source":"ClinicalTrials","ids":["NCT00482053"]}],"maxPhaseForIndication":2},{"disease":"EFO_0009847","efoName":"dizziness","references":[{"source":"DailyMed","ids":["0998947c-cfba-497e-bf7a-9c7f8fff1764"]}],"maxPhaseForIndication":4},{"disease":"EFO_0005531","efoName":"urticaria","references":[{"source":"ClinicalTrials","ids":["NCT00866788","NCT01264939","NCT02023164","NCT02935699"]}],"maxPhaseForIndication":3},{"disease":"EFO_0005854","efoName":"allergic rhinitis","references":[{"source":"DailyMed","ids":["079de233-aacb-47d3-90fe-d66f1ca7bb15","7abace52-4d9c-429b-b9a9-96d06261ef50","739aedfd-d5b8-4be8-9453-c7229ec79e26"]}],"maxPhaseForIndication":4},{"disease":"EFO_0004599","efoName":"acute graft vs. host disease","references":[{"source":"ClinicalTrials","ids":["NCT00771875"]}],"maxPhaseForIndication":2},{"disease":"EFO_0007160","efoName":"autoimmune thrombocytopenic purpura","references":[{"source":"ClinicalTrials","ids":["NCT04741139"]}],"maxPhaseForIndication":1},{"disease":"EFO_0002690","efoName":"systemic lupus erythematosus","references":[{"source":"ClinicalTrials","ids":["NCT00076752","NCT00137969","NCT00381810"]}],"maxPhaseForIndication":3},{"disease":"EFO_0000616","efoName":"neoplasm","references":[{"source":"ClinicalTrials","ids":["NCT02648490","NCT03324113","NCT04401020"]}],"maxPhaseForIndication":2},{"disease":"HP_0012735","efoName":"cough","references":[{"source":"ClinicalTrials","ids":["NCT01177852"]}],"maxPhaseForIndication":3},{"disease":"MONDO_0001056","efoName":"gastric cancer","references":[{"source":"ClinicalTrials","ids":["NCT04308837"]}],"maxPhaseForIndication":2},{"disease":"EFO_0003086","efoName":"kidney disease","references":[{"source":"ClinicalTrials","ids":["NCT00078559","NCT04629248"]}],"maxPhaseForIndication":3},{"disease":"HP_0002013","efoName":"vomiting","references":[{"source":"DailyMed","ids":["bc71539e-1a33-4709-8a24-c2894e8dbc1c","056b6032-c92d-458e-97d4-a964d1adb38a","0998947c-cfba-497e-bf7a-9c7f8fff1764"]}],"maxPhaseForIndication":4},{"disease":"EFO_0003938","efoName":"aphthous ulcer","references":[{"source":"ClinicalTrials","ids":["NCT01293968"]}],"maxPhaseForIndication":2},{"disease":"MONDO_0008903","efoName":"lung cancer","references":[{"source":"ClinicalTrials","ids":["NCT01455389"]}],"maxPhaseForIndication":1},{"disease":"EFO_0005230","efoName":"anxiety","references":[{"source":"ClinicalTrials","ids":["NCT02374567"]}],"maxPhaseForIndication":3},{"disease":"MONDO_0005090","efoName":"schizophrenia","references":[{"source":"ClinicalTrials","ids":["NCT02374567"]}],"maxPhaseForIndication":3},{"disease":"EFO_0005592","efoName":"t-cell leukemia","references":[{"source":"ClinicalTrials","ids":["NCT02999633"]}],"maxPhaseForIndication":2},{"disease":"MONDO_0007079","efoName":"alcohol dependence","references":[{"source":"ClinicalTrials","ids":["NCT02061293"]}],"maxPhaseForIndication":2},{"disease":"EFO_0005761","efoName":"lupus nephritis","references":[{"source":"ClinicalTrials","ids":["NCT00282347","NCT02260934","NCT04221477"]}],"maxPhaseForIndication":3},{"disease":"EFO_0000274","efoName":"atopic eczema","references":[{"source":"ClinicalTrials","ids":["NCT03688464"]}],"maxPhaseForIndication":0}],"approvedIndications":["EFO_0005854","EFO_0006928","HP_0000989","HP_0012735","EFO_0003958","MONDO_0005271","EFO_0009516","HP_0001742","EFO_0004698","EFO_0007214","HP_0002018","HP_0002017","HP_0002013","EFO_0009847","EFO_0003956"],"indicationCount":78}
{"id":"CHEMBL2017974","indications":[{"disease":"MONDO_0007576","efoName":"esophageal cancer","references":[{"source":"ClinicalTrials","ids":["NCT01806649"]}],"maxPhaseForIndication":2},{"disease":"EFO_1001951","efoName":"colorectal carcinoma","references":[{"source":"ClinicalTrials","ids":["NCT01304602"]}],"maxPhaseForIndication":1},{"disease":"Orphanet_44890","efoName":"gastrointestinal stromal tumor","references":[{"source":"ClinicalTrials","ids":["NCT01468688"]}],"maxPhaseForIndication":1},{"disease":"EFO_0000181","efoName":"head and neck squamous cell carcinoma","references":[{"source":"ClinicalTrials","ids":["NCT01527877","NCT01852292"]}],"maxPhaseForIndication":2},{"disease":"EFO_0000702","efoName":"small cell lung carcinoma","references":[{"source":"ClinicalTrials","ids":["NCT02194049"]}],"maxPhaseForIndication":1},{"disease":"EFO_0000616","efoName":"neoplasm","references":[{"source":"ClinicalTrials","ids":["NCT01155453","NCT01283503","NCT01363232","NCT01540253","NCT01833169","NCT02439489"]}],"maxPhaseForIndication":2},{"disease":"EFO_0000756","efoName":"melanoma","references":[{"source":"ClinicalTrials","ids":["NCT02159066","NCT02452294"]}],"maxPhaseForIndication":2},{"disease":"EFO_0003086","efoName":"kidney disease","references":[{"source":"ClinicalTrials","ids":["NCT02048787"]}],"maxPhaseForIndication":1},{"disease":"MONDO_0018906","efoName":"follicular lymphoma","references":[{"source":"ClinicalTrials","ids":["NCT02756247"]}],"maxPhaseForIndication":1},{"disease":"MONDO_0044903","efoName":"myelofibrosis","references":[{"source":"ClinicalTrials","ids":["NCT01730248"]}],"maxPhaseForIndication":1},{"disease":"MONDO_0011962","efoName":"endometrial cancer","references":[{"source":"ClinicalTrials","ids":["NCT01289041","NCT01397877","NCT01550380"]}],"maxPhaseForIndication":2},{"disease":"MONDO_0002108","efoName":"thyroid cancer","references":[{"source":"ClinicalTrials","ids":["NCT01830504"]}],"maxPhaseForIndication":2},{"disease":"EFO_0000519","efoName":"glioblastoma multiforme","references":[{"source":"ClinicalTrials","ids":["NCT01339052","NCT01349660","NCT01870726","NCT01934361"]}],"maxPhaseForIndication":2},{"disease":"EFO_0003869","efoName":"breast neoplasm","references":[{"source":"ClinicalTrials","ids":["NCT01953445"]}],"maxPhaseForIndication":3},{"disease":"EFO_0006859","efoName":"head and neck malignant neoplasia","references":[{"source":"ClinicalTrials","ids":["NCT04338399"]}],"maxPhaseForIndication":3},{"disease":"EFO_1000581","efoName":"thymoma","references":[{"source":"ClinicalTrials","ids":["NCT02220855"]}],"maxPhaseForIndication":2},{"disease":"MONDO_0008903","efoName":"lung cancer","references":[{"source":"ClinicalTrials","ids":["NCT01470209"]}],"maxPhaseForIndication":1},{"disease":"MONDO_0007254","efoName":"breast cancer","references":[{"source":"ClinicalTrials","ids":["NCT01132664","NCT01248494","NCT01339442","NCT01513356","NCT01572727","NCT01610284","NCT01626209","NCT01629615","NCT01633060","NCT01790932","NCT01816594","NCT01923168","NCT02058381","NCT02088684","NCT02154776","NCT02404844"]}],"maxPhaseForIndication":3},{"disease":"EFO_1001469","efoName":"mantle cell lymphoma","references":[{"source":"ClinicalTrials","ids":["NCT01693614","NCT02756247"]}],"maxPhaseForIndication":2},{"disease":"EFO_0003060","efoName":"non-small cell lung carcinoma","references":[{"source":"ClinicalTrials","ids":["NCT01297491","NCT01723800","NCT01820325","NCT01911325","NCT01971489","NCT02128724"]}],"maxPhaseForIndication":2},{"disease":"MONDO_0002974","efoName":"cervical cancer","references":[{"source":"ClinicalTrials","ids":["NCT01613677"]}],"maxPhaseForIndication":2},{"disease":"EFO_0000095","efoName":"chronic lymphocytic leukemia","references":[{"source":"ClinicalTrials","ids":["NCT02340780","NCT02614508"]}],"maxPhaseForIndication":2},{"disease":"EFO_0000403","efoName":"diffuse large b-cell lymphoma","references":[{"source":"ClinicalTrials","ids":["NCT02756247"]}],"maxPhaseForIndication":1},{"disease":"MONDO_0008315","efoName":"prostate cancer","references":[{"source":"ClinicalTrials","ids":["NCT01385293","NCT01634061","NCT01695473","NCT01741753"]}],"maxPhaseForIndication":2},{"disease":"EFO_0000565","efoName":"leukemia","references":[{"source":"ClinicalTrials","ids":["NCT01396499"]}],"maxPhaseForIndication":1},{"disease":"EFO_0001421","efoName":"liver disease","references":[{"source":"ClinicalTrials","ids":["NCT01727128"]}],"maxPhaseForIndication":1}],"approvedIndications":[],"indicationCount":26}
{"id":"CHEMBL1201458","indications":[{"disease":"MONDO_0000831","efoName":"thrombotic disease","references":[{"source":"ClinicalTrials","ids":["NCT02971345"]}],"maxPhaseForIndication":3},{"disease":"EFO_0000182","efoName":"hepatocellular carcinoma","references":[{"source":"ClinicalTrials","ids":["NCT01126463","NCT01861912","NCT01966133","NCT02585479","NCT02630108","NCT02638857","NCT02755311","NCT02762266","NCT02971345","NCT03192644","NCT04178642"]}],"maxPhaseForIndication":3},{"disease":"MONDO_0005178","efoName":"osteoarthritis","references":[{"source":"ClinicalTrials","ids":["NCT04733092"]}],"maxPhaseForIndication":1},{"disease":"MONDO_0002691","efoName":"liver cancer","references":[{"source":"ClinicalTrials","ids":["NCT00870558","NCT01877187"]}],"maxPhaseForIndication":3},{"disease":"EFO_0000616","efoName":"neoplasm","references":[{"source":"DailyMed","ids":["511d1f64-5cb9-4baa-a123-96205467e59a"]}],"maxPhaseForIndication":4}],"approvedIndications":["EFO_0000616"],"indicationCount":5}
{"id":"CHEMBL50300","indications":[{"disease":"EFO_0000763","efoName":"viral disease","references":[{"source":"ATC","ids":["J05AD02"]}],"maxPhaseForIndication":0}],"approvedIndications":[],"indicationCount":1}
{"id":"CHEMBL2105741","indications":[{"disease":"MONDO_0008903","efoName":"lung cancer","references":[{"source":"DailyMed","ids":["0002ad27-779d-42ab-83b5-bc65453412a1"]}],"maxPhaseForIndication":4},{"disease":"EFO_0000389","efoName":"cutaneous melanoma","references":[{"source":"ClinicalTrials","ids":["NCT02196181","NCT04527549"]}],"maxPhaseForIndication":4},{"disease":"EFO_0002617","efoName":"metastatic melanoma","references":[{"source":"FDA","ids":["label/2013/204114s000lbl.pdf"]}],"maxPhaseForIndication":4},{"disease":"EFO_1000926","efoName":"erdheim-chester disease","references":[{"source":"ClinicalTrials","ids":["NCT03794297"]}],"maxPhaseForIndication":2},{"disease":"EFO_0000311","efoName":"cancer","references":[{"source":"ClinicalTrials","ids":["NCT01416337","NCT01725100"]}],"maxPhaseForIndication":1},{"disease":"EFO_0001378","efoName":"multiple myeloma","references":[{"source":"ClinicalTrials","ids":["NCT04439279","NCT04439292","NCT04439318","NCT04439357"]}],"maxPhaseForIndication":2},{"disease":"MONDO_0002108","efoName":"thyroid cancer","references":[{"source":"DailyMed","ids":["0002ad27-779d-42ab-83b5-bc65453412a1"]}],"maxPhaseForIndication":4}],"approvedIndications":["MONDO_0002108","EFO_0000389","MONDO_0008903","EFO_0002617"],"indicationCount":7}
{"id":"CHEMBL1201236","indications":[{"disease":"EFO_0002610","efoName":"cocaine dependence","references":[{"source":"ClinicalTrials","ids":["NCT00218023","NCT00218075","NCT01393457","NCT01437293","NCT01468012","NCT02080819"]}],"maxPhaseForIndication":2},{"disease":"MONDO_0004976","efoName":"amyotrophic lateral sclerosis","references":[{"source":"ClinicalTrials","ids":["NCT03929068"]}],"maxPhaseForIndication":1},{"disease":"EFO_0003843","efoName":"pain","references":[{"source":"ClinicalTrials","ids":["NCT02116790"]}],"maxPhaseForIndication":2},{"disease":"MONDO_0005090","efoName":"schizophrenia","references":[{"source":"ClinicalTrials","ids":["NCT01636037"]}],"maxPhaseForIndication":2},{"disease":"Orphanet_55","efoName":"oculocutaneous albinism","references":[{"source":"ClinicalTrials","ids":["NCT01663935"]}],"maxPhaseForIndication":2},{"disease":"EFO_0000712","efoName":"stroke","references":[{"source":"ClinicalTrials","ids":["NCT01429077","NCT03735901"]}],"maxPhaseForIndication":3},{"disease":"EFO_0005687","efoName":"fibromyalgia","references":[{"source":"ClinicalTrials","ids":["NCT01323374"]}],"maxPhaseForIndication":2},{"disease":"EFO_1001402","efoName":"postencephalitic parkinson disease","references":[{"source":"DailyMed","ids":["ff8e105b-7415-42d4-bbb2-b36cfb8945a5"]}],"maxPhaseForIndication":4},{"disease":"MONDO_0001020","efoName":"amblyopia","references":[{"source":"ClinicalTrials","ids":["NCT00789672","NCT01190813"]}],"maxPhaseForIndication":3},{"disease":"HP_0002381","efoName":"aphasia","references":[{"source":"ClinicalTrials","ids":["NCT01429077"]}],"maxPhaseForIndication":2},{"disease":"MONDO_0005301","efoName":"multiple sclerosis","references":[{"source":"ClinicalTrials","ids":["NCT03266965","NCT04764383"]}],"maxPhaseForIndication":2},{"disease":"Orphanet_791","efoName":"retinitis pigmentosa","references":[{"source":"ClinicalTrials","ids":["NCT02837640"]}],"maxPhaseForIndication":2},{"disease":"Orphanet_1764","efoName":"familial dysautonomia","references":[{"source":"ClinicalTrials","ids":["NCT01212484","NCT02553265"]}],"maxPhaseForIndication":3},{"disease":"EFO_0005252","efoName":"orthostatic hypotension","references":[{"source":"ClinicalTrials","ids":["NCT00223691"]}],"maxPhaseForIndication":1},{"disease":"MONDO_0005180","efoName":"parkinson disease","references":[{"source":"DailyMed","ids":["d7c6da26-42a7-4743-be02-3a233434eef2","d5204e5e-10ef-4758-8fc6-cb710048c687","644b8392-276e-2751-ce27-bd8c10b2bb2c","c1f90c86-9ce6-477b-a2e3-66f82b378f5f","043db807-8381-4df8-b3a3-825988d63ef5","a5bcaa6d-a9fe-4f3e-8fac-b790c24e8658","e0c559ce-5c6c-4b0d-8db8-5ed3112832b0","a806d23f-5818-44bf-8e0c-10ecb7c2b0a9","b4b398bc-399c-4832-adef-baf2019c633d","d2a64f14-f638-49d9-8a96-cb7ae46ac3ea","3c768639-8a70-4d12-ad93-827bb42ec6b7","f1a334d2-129c-49f9-bd29-6bb0838085fe","a15f5833-42f0-4890-9596-992eef0846e5","33fbe430-b429-43c0-a3f1-9cf016ff23af","abff005f-23fc-4d1e-b469-88aa07589a43","79e4ca99-7217-41bb-8ace-d0040b56e859","48e0f2ec-b217-4c25-a71c-20e173d05edb","5217a6ec-cc26-4acc-b2da-17f6545c3b60","5edfc3e7-f80d-47ee-897a-c02ff4eb3e74","d26b56fa-d521-461b-a619-40b65862b644","829c35f9-ace0-11dd-8800-f3e252b43544","8edc4a14-f8b2-48cf-8478-ed51f2047d27","16f9e4d1-6953-4d4f-b4cf-ad95a856ac25","58a6e76a-f99f-4f0c-9d83-a55a30edda97","8f03374a-70a1-45e8-83e7-ee0f3f0541a1","0c56144f-6aaa-4408-a007-2650f030cec2","3a4f4d6f-e99d-4003-9a58-d7fd377a69e9","bf85a378-6a09-4b35-b145-0624b1864241","0caee228-12c7-437c-9ea6-06b4e51722e1","77bf4f54-6ab2-49b4-ba55-56291fccf7b3","f1d6c0c3-6bff-4ea2-bcf8-0d679b5ccc6d","a7b37778-d198-4799-8bf0-92576cff02b9","c47856c9-7013-44a2-b381-4ca67e1d1b4c","2f3b8f28-b3da-4658-bdc4-fe86dec62d32","43b4927e-7880-4050-b27f-ee59f65f751c","69e575b9-f8a5-494f-b736-2520ef505cb0","332d95c6-a356-4aef-b44c-ce286575d25c","d17e17d5-f73a-49c5-b1bd-2543cc486edf","2b9d6e2d-40e0-433c-a8f4-c1a61ccc2015","11587fa6-dc2c-44a5-85c6-85ec40c6b9b1","e1ff4c1f-5d6f-44a6-a0f6-d7ca2a94adb9","76a7297a-4782-4ca2-9c77-8e3662a512dc","ff8e105b-7415-42d4-bbb2-b36cfb8945a5","dcb0fb25-ad60-4ab6-bc0f-ebc356357d93","486a7e4b-ef1d-2d2c-dcb9-76ae0b69a70a","52ce2492-89ab-40a5-9ab7-9b44fbb712d4","6c1f7cd4-de56-45c1-a734-5e77b4aeb6f7","a355d5f2-407d-40fa-a374-b3632261ea4a","0d31ce9a-e5bf-4968-8108-a137898ac262","4cb3471c-c68f-48f6-a5d0-ebaa2531c0ef","9b993fc7-e026-4749-b785-cbd3b9c29003"]},{"source":"ClinicalTrials","ids":["NCT00099268","NCT00125567","NCT00134966","NCT00141518","NCT00143026","NCT00174239","NCT00200447","NCT00219284","NCT00253084","NCT00279825","NCT00335153","NCT00357994","NCT00360568","NCT00391898","NCT00491998","NCT00505843","NCT00558337","NCT00562198","NCT00590122","NCT00601978","NCT00642356","NCT00660387","NCT00660673","NCT00745277","NCT00845000","NCT00888186","NCT00906828","NCT00914602","NCT00918177","NCT01070628","NCT01171313","NCT01227655","NCT01229332","NCT01296464","NCT01399905","NCT01479127","NCT01484990","NCT01515410","NCT01519284","NCT01533116","NCT01568034","NCT01568047","NCT01568073","NCT01617135","NCT01725802","NCT01736176","NCT01766258","NCT01883505","NCT01960842","NCT02096601","NCT02169414","NCT02170376","NCT02271503","NCT02312232","NCT02480803","NCT02486432","NCT02549092","NCT02554734","NCT02577523","NCT02799381","NCT03103399","NCT03115827","NCT03140956","NCT03496870","NCT03576638","NCT03887884","NCT04006210","NCT04513340","NCT04591535","NCT04952194"]}],"maxPhaseForIndication":4},{"disease":"EFO_0003768","efoName":"nicotine dependence","references":[{"source":"ClinicalTrials","ids":["NCT02633839"]}],"maxPhaseForIndication":1},{"disease":"EFO_0000546","efoName":"injury","references":[{"source":"DailyMed","ids":["d7c6da26-42a7-4743-be02-3a233434eef2","e1ff4c1f-5d6f-44a6-a0f6-d7ca2a94adb9","ff8e105b-7415-42d4-bbb2-b36cfb8945a5"]}],"maxPhaseForIndication":4},{"disease":"HP_0003418","efoName":"back pain","references":[{"source":"ClinicalTrials","ids":["NCT04082715"]}],"maxPhaseForIndication":2},{"disease":"Orphanet_72","efoName":"angelman syndrome","references":[{"source":"ClinicalTrials","ids":["NCT00829439"]}],"maxPhaseForIndication":1},{"disease":"EFO_1001175","efoName":"secondary parkinson disease","references":[{"source":"DailyMed","ids":["ff8e105b-7415-42d4-bbb2-b36cfb8945a5"]}],"maxPhaseForIndication":4},{"disease":"MONDO_0004979","efoName":"asthma","references":[{"source":"ClinicalTrials","ids":["NCT02633007"]}],"maxPhaseForIndication":1},{"disease":"EFO_0003888","efoName":"attention deficit hyperactivity disorder","references":[{"source":"ClinicalTrials","ids":["NCT00983814"]}],"maxPhaseForIndication":2},{"disease":"EFO_0000537","efoName":"hypertension","references":[{"source":"ClinicalTrials","ids":["NCT00223717"]}],"maxPhaseForIndication":1},{"disease":"EFO_1001919","efoName":"spinal cord injury","references":[{"source":"ClinicalTrials","ids":["NCT01484184","NCT04000919","NCT04052776","NCT04520178"]}],"maxPhaseForIndication":2},{"disease":"EFO_0001365","efoName":"age-related macular degeneration","references":[{"source":"ClinicalTrials","ids":["NCT02873351","NCT03022318","NCT03023059","NCT03451500"]}],"maxPhaseForIndication":2}],"approvedIndications":["EFO_0000546","EFO_1001175","MONDO_0005180","EFO_1001402"],"indicationCount":25}
{"id":"CHEMBL2103825","indications":[{"disease":"EFO_0001073","efoName":"obesity","references":[{"source":"ClinicalTrials","ids":["NCT00148382"]}],"maxPhaseForIndication":1}],"approvedIndications":[],"indicationCount":1}
{"id":"CHEMBL1200490","indications":[{"disease":"EFO_0000660","efoName":"polycystic ovary syndrome","references":[{"source":"ClinicalTrials","ids":["NCT01185704"]}],"maxPhaseForIndication":3},{"disease":"Orphanet_64739","efoName":"ovarian hyperstimulation syndrome","references":[{"source":"ClinicalTrials","ids":["NCT01109888","NCT01268761"]}],"maxPhaseForIndication":3},{"disease":"EFO_0001065","efoName":"endometriosis","references":[{"source":"ClinicalTrials","ids":["NCT00244452"]}],"maxPhaseForIndication":2},{"disease":"EFO_0000545","efoName":"infertility","references":[{"source":"ClinicalTrials","ids":["NCT01079949","NCT02333253","NCT02640976","NCT02823080","NCT03809429","NCT04537078"]}],"maxPhaseForIndication":3},{"disease":"EFO_0000545","efoName":"infertility","references":[{"source":"ClinicalTrials","ids":["NCT03373149","NCT04268927"]}],"maxPhaseForIndication":2},{"disease":"EFO_0000284","efoName":"benign prostatic hyperplasia","references":[{"source":"ClinicalTrials","ids":["NCT00449150","NCT00663858","NCT00670306"]}],"maxPhaseForIndication":3},{"disease":"EFO_0000685","efoName":"rheumatoid arthritis","references":[{"source":"ClinicalTrials","ids":["NCT00667758"]}],"maxPhaseForIndication":2}],"approvedIndications":[],"indicationCount":7}
{"id":"CHEMBL1172","indications":[{"disease":"HP_0000964","efoName":"eczema","references":[{"source":"ClinicalTrials","ids":["NCT01916980"]}],"maxPhaseForIndication":3},{"disease":"EFO_0003060","efoName":"non-small cell lung carcinoma","references":[{"source":"ClinicalTrials","ids":["NCT02646020"]}],"maxPhaseForIndication":2},{"disease":"EFO_0005854","efoName":"allergic rhinitis","references":[{"source":"ClinicalTrials","ids":["NCT00405964","NCT00789152","NCT00794378","NCT00794794","NCT01529229","NCT01720485","NCT02507635"]},{"source":"DailyMed","ids":["d4e3bd9e-54a0-4546-8d38-a1d0190a81a4","d8ea45de-a6b5-5f33-468b-acf1396fb953","5b84ba42-3136-4373-8953-49e58a6c8784","e5d1f465-e436-b4fd-d351-07a7b2acb440","fae16319-a411-470d-8a44-f218749c6885","91ce2b02-8f8e-4929-a962-b8f88a40b70a","456ee8f5-3e49-4b22-9c4b-6d7bd4adec53","759fc3c9-fd97-6067-5109-8fcf170a476a","58ba2dc8-10c2-4532-92e2-40ec2fee3378","5b79aff4-9bed-429d-8def-a7929293387d","dbb8e695-f00b-4c67-bd49-09a1ae5bb669","2a90b899-7746-43dc-ac8a-e754428eb30c","eb25ecc8-5989-48c7-847e-e51f942a82ff","4b546121-ef6b-458c-ae0c-ce5bba3dc9a3"]}],"maxPhaseForIndication":4},{"disease":"EFO_0000274","efoName":"atopic eczema","references":[{"source":"ClinicalTrials","ids":["NCT00817076"]}],"maxPhaseForIndication":3},{"disease":"Orphanet_79292","efoName":"fish-eye disease","references":[{"source":"ClinicalTrials","ids":["NCT01314352"]}],"maxPhaseForIndication":1},{"disease":"EFO_0003956","efoName":"seasonal allergic rhinitis","references":[{"source":"DailyMed","ids":["61a1562b-46c6-40ed-af02-305342e76e2f","d4e3bd9e-54a0-4546-8d38-a1d0190a81a4","d8ea45de-a6b5-5f33-468b-acf1396fb953","5b84ba42-3136-4373-8953-49e58a6c8784","e5d1f465-e436-b4fd-d351-07a7b2acb440","fae16319-a411-470d-8a44-f218749c6885","91ce2b02-8f8e-4929-a962-b8f88a40b70a","456ee8f5-3e49-4b22-9c4b-6d7bd4adec53","759fc3c9-fd97-6067-5109-8fcf170a476a","58ba2dc8-10c2-4532-92e2-40ec2fee3378","c7230a68-a3ac-4dce-9e72-6e21f0b25f45","5b79aff4-9bed-429d-8def-a7929293387d","dbb8e695-f00b-4c67-bd49-09a1ae5bb669","2a90b899-7746-43dc-ac8a-e754428eb30c","eb25ecc8-5989-48c7-847e-e51f942a82ff","4b546121-ef6b-458c-ae0c-ce5bba3dc9a3"]},{"source":"ClinicalTrials","ids":["NCT00406783","NCT00783133","NCT00783146","NCT00783211","NCT00794248","NCT00794495","NCT00794599","NCT00794768","NCT00794846","NCT00805584","NCT00816972","NCT00862225","NCT00867191","NCT01108783","NCT01400828","NCT02320396"]}],"maxPhaseForIndication":4},{"disease":"EFO_0007141","efoName":"allergic conjunctivitis","references":[{"source":"ClinicalTrials","ids":["NCT01740284"]}],"maxPhaseForIndication":3},{"disease":"MONDO_0002406","efoName":"dermatitis","references":[{"source":"ClinicalTrials","ids":["NCT01916980"]}],"maxPhaseForIndication":3},{"disease":"HP_0000989","efoName":"pruritus","references":[{"source":"ClinicalTrials","ids":["NCT01916980"]}],"maxPhaseForIndication":3},{"disease":"MONDO_0005271","efoName":"allergic disease","references":[{"source":"ClinicalTrials","ids":["NCT00359138","NCT00633919","NCT00779116","NCT00779636","NCT00780403","NCT01529242"]},{"source":"ATC","ids":["R06AX27"]}],"maxPhaseForIndication":4},{"disease":"EFO_0007214","efoName":"common cold","references":[{"source":"ClinicalTrials","ids":["NCT02904304"]}],"maxPhaseForIndication":3},{"disease":"EFO_0005531","efoName":"urticaria","references":[{"source":"DailyMed","ids":["759fc3c9-fd97-6067-5109-8fcf170a476a","58ba2dc8-10c2-4532-92e2-40ec2fee3378","5b79aff4-9bed-429d-8def-a7929293387d","d4e3bd9e-54a0-4546-8d38-a1d0190a81a4","d8ea45de-a6b5-5f33-468b-acf1396fb953","5b84ba42-3136-4373-8953-49e58a6c8784","dbb8e695-f00b-4c67-bd49-09a1ae5bb669","eb25ecc8-5989-48c7-847e-e51f942a82ff","4b546121-ef6b-458c-ae0c-ce5bba3dc9a3","fae16319-a411-470d-8a44-f218749c6885"]},{"source":"ClinicalTrials","ids":["NCT00264303","NCT00536380","NCT00598611","NCT00751166","NCT00751218","NCT00783354","NCT00795158","NCT00795522","NCT01444196","NCT01916967","NCT01940393"]}],"maxPhaseForIndication":4},{"disease":"EFO_1001417","efoName":"rhinitis, allergic, perennial","references":[{"source":"ClinicalTrials","ids":["NCT00406783","NCT01918033"]}],"maxPhaseForIndication":3}],"approvedIndications":["EFO_0005854","EFO_0005531","MONDO_0005271","EFO_0003956"],"indicationCount":13}
{"id":"CHEMBL129","indications":[{"disease":"EFO_1001365","efoName":"lymphoma, aids-related","references":[{"source":"ClinicalTrials","ids":["NCT00002524"]}],"maxPhaseForIndication":2},{"disease":"MONDO_0019471","efoName":"adult t-cell leukemia/lymphoma","references":[{"source":"ClinicalTrials","ids":["NCT02737046"]}],"maxPhaseForIndication":2},{"disease":"EFO_0000763","efoName":"viral disease","references":[{"source":"ATC","ids":["J05AF01"]}],"maxPhaseForIndication":4},{"disease":"EFO_0000180","efoName":"hiv-1 infection","references":[{"source":"ClinicalTrials","ids":["NCT00098293","NCT00799864","NCT00915655","NCT01352715","NCT01714414"]}],"maxPhaseForIndication":4},{"disease":"EFO_0007137","efoName":"aids related complex","references":[{"source":"ClinicalTrials","ids":["NCT00001267"]}],"maxPhaseForIndication":3},{"disease":"Orphanet_3389","efoName":"tuberculosis","references":[{"source":"ClinicalTrials","ids":["NCT00078247"]}],"maxPhaseForIndication":3},{"disease":"EFO_0007448","efoName":"pneumocystosis","references":[{"source":"ClinicalTrials","ids":["NCT00000727","NCT00000991"]}],"maxPhaseForIndication":3},{"disease":"EFO_0007527","efoName":"tropical spastic paraparesis","references":[{"source":"ClinicalTrials","ids":["NCT00272480","NCT02655471"]}],"maxPhaseForIndication":2},{"disease":"Orphanet_183660","efoName":"severe combined immunodeficiency","references":[{"source":"ClinicalTrials","ids":["NCT00018018"]}],"maxPhaseForIndication":1},{"disease":"EFO_0002608","efoName":"aids dementia","references":[{"source":"ClinicalTrials","ids":["NCT00000657","NCT00000702","NCT00000709"]}],"maxPhaseForIndication":3},{"disease":"HP_0002014","efoName":"diarrhea","references":[{"source":"ClinicalTrials","ids":["NCT00650637"]}],"maxPhaseForIndication":3},{"disease":"EFO_0000574","efoName":"lymphoma","references":[{"source":"ClinicalTrials","ids":["NCT00002905","NCT00003261","NCT00006264","NCT00041327","NCT00217503"]}],"maxPhaseForIndication":2},{"disease":"EFO_0000765","efoName":"aids","references":[{"source":"ClinicalTrials","ids":["NCT00001267","NCT00001354","NCT00144183","NCT00197613","NCT00433056","NCT00966160","NCT01469520","NCT02369406","NCT03178084"]}],"maxPhaseForIndication":3},{"disease":"EFO_0000558","efoName":"kaposi's sarcoma","references":[{"source":"ClinicalTrials","ids":["NCT00834457"]}],"maxPhaseForIndication":2},{"disease":"EFO_0002950","efoName":"pregnancy","references":[{"source":"ClinicalTrials","ids":["NCT00000751"]}],"maxPhaseForIndication":3},{"disease":"MONDO_0015564","efoName":"castleman disease","references":[{"source":"ClinicalTrials","ids":["NCT01441063"]}],"maxPhaseForIndication":2},{"disease":"MONDO_0100096","efoName":"covid-19","references":[{"source":"ClinicalTrials","ids":["NCT04358081"]}],"maxPhaseForIndication":3},{"disease":"EFO_0000764","efoName":"hiv infection","references":[{"source":"DailyMed","ids":["e816e8f5-1e50-4f49-8bea-92da0121d26e","f5f7c0d9-a247-4308-8269-32accc490ea6","221a4135-70e1-4913-bd54-f4b84bb4001b","425faad5-8dbc-455b-a8c3-60bdf0e2ce54","4ce97d53-e852-49ad-92e3-24031a115e26","9a2c643d-5c5f-4427-804d-8b0eb9797157","fc2d6065-7806-457c-82e1-04bb19e57b8c","da2d3a56-a124-46cd-93bf-82b3c419536b","4d7df84d-256e-48c9-b164-254d5bce1eb7","abd503f4-6de8-41e2-95fa-2496610508ad","4ccc8192-fc3a-4671-a7ce-5565a7b5aaef","51abd2ce-6be1-412d-b806-5f24935ac5e3","cd3f2a72-3f01-49ba-9efe-9f2e6fedbd01","2c3264a4-1194-46a0-9343-927da4eda5b8","5ac42750-b856-4f4f-bc05-2758c3035250","98dfecf6-dbaf-4ef5-9fda-d11f90f6aa58","56467b20-c2c0-416a-8e6e-931bac559f7f","3354e50f-4dc5-413f-b5ae-87353ab8913d","54e21b7b-939c-4afa-9492-bde2b36dd352","d851ebb0-2370-4363-925c-628ba7fbc221","6df09f15-b102-431c-adde-d7aeef6f5d84","c08ed05f-89ff-4620-8bc6-60419fa02131","d41fdad8-c67a-4fc8-a775-5b5c41c0b0e7","16da660b-9981-4d24-a14a-94c7744fce4f","e4eee396-fdf4-4e4b-94c2-930af5609a7d","e7c8ddef-005d-4f1c-8c1a-ea84044ab4d4","536735fc-566c-4ad4-b83e-602199ff82b4","27370999-074b-4674-8655-e998419ec9d7","a3c2532a-5880-4d52-b2a1-2e6d4dbd6021","b3d75ea7-66d5-44e9-9251-0e5967e8501b","d8540843-055c-47fb-9cff-81e64b1d41c3","0bdae7bd-2d03-4948-baa3-73532602b2ef","9907acb2-e4a0-46f9-93c0-a8d7b7ce98cf","1bc4c6c8-7e75-494e-810b-8f83135a3204","d346d08d-ebb5-4500-923f-fe111f304876","1b34c6ec-ac27-455e-976e-d22cf9d81950","29489c0e-e981-4bc0-beaf-05c9a9c55c1f","1a123145-2d63-484a-a0a0-061890796137","479a2784-8db2-4fe5-94ba-55316a3c4e4f","d9370dfc-283b-4a91-8e5e-18c35d2a78e6","8381ce12-92fa-4cab-b45f-f65ed3d0197b","ca9f0c57-fc8b-4da4-a987-0fc52b7fd4f4","c2dbe442-bd0c-40bf-be76-b18595676dc2","86dccc6d-83f3-4934-8ffa-b2e92ea08f86","4255bf9a-b114-474b-b310-f22ff048b2a6","633ac0f4-576f-b556-650b-a5e7af39b4ad","e62ae0e4-0689-431a-a552-f0711ca68844","90355e89-87d0-456a-87c1-c25bae12affc","64b73211-b156-4a8b-b6f6-4b97f82bfc43","9681028f-9b57-4266-b1c5-4b04205d2df4","b03e286a-4d44-489a-89d0-ee563e1f280f","9b32f5a4-d0f7-486b-b699-8dc9202b6869"]},{"source":"ClinicalTrials","ids":["NCT00000625","NCT00000628","NCT00000629","NCT00000637","NCT00000649","NCT00000651","NCT00000652","NCT00000656","NCT00000657","NCT00000659","NCT00000661","NCT00000664","NCT00000671","NCT00000678","NCT00000679","NCT00000680","NCT00000682","NCT00000685","NCT00000696","NCT00000700","NCT00000701","NCT00000702","NCT00000705","NCT00000711","NCT00000712","NCT00000716","NCT00000720","NCT00000727","NCT00000728","NCT00000736","NCT00000742","NCT00000743","NCT00000750","NCT00000751","NCT00000753","NCT00000754","NCT00000755","NCT00000760","NCT00000770","NCT00000781","NCT00000789","NCT00000791","NCT00000800","NCT00000803","NCT00000810","NCT00000814","NCT00000818","NCT00000823","NCT00000831","NCT00000834","NCT00000838","NCT00000841","NCT00000864","NCT00000865","NCT00000870","NCT00000872","NCT00000882","NCT00000885","NCT00000891","NCT00000902","NCT00000903","NCT00000916","NCT00000918","NCT00000944","NCT00000952","NCT00000960","NCT00000961","NCT00000967","NCT00000976","NCT00000978","NCT00000979","NCT00000982","NCT00000983","NCT00000986","NCT00000990","NCT00000991","NCT00000994","NCT00000999","NCT00001002","NCT00001005","NCT00001007","NCT00001010","NCT00001011","NCT00001022","NCT00001025","NCT00001029","NCT00001032","NCT00001036","NCT00001040","NCT00001045","NCT00001049","NCT00001057","NCT00001063","NCT00001066","NCT00001067","NCT00001083","NCT00001084","NCT00001085","NCT00001087","NCT00001094","NCT00001095","NCT00001104","NCT00001112","NCT00001282","NCT00001644","NCT00001989","NCT00001993","NCT00002006","NCT00002014","NCT00002079","NCT00002086","NCT00002109","NCT00002110","NCT00002117","NCT00002124","NCT00002162","NCT00002179","NCT00002183","NCT00002184","NCT00002190","NCT00002195","NCT00002199","NCT00002208","NCT00002238","NCT00002255","NCT00002320","NCT00002322","NCT00002324","NCT00002326","NCT00002334","NCT00002347","NCT00002357","NCT00002367","NCT00002371","NCT00002376","NCT00002378","NCT00002379","NCT00002386","NCT00002389","NCT00002391","NCT00002409","NCT00002410","NCT00002429","NCT00002435","NCT00002436","NCT00004585","NCT00004736","NCT00004852","NCT00004981","NCT00004998","NCT00004999","NCT00005000","NCT00005002","NCT00005106","NCT00006396","NCT00011895","NCT00013520","NCT00013897","NCT00014014","NCT00017719","NCT00028327","NCT00031070","NCT00038506","NCT00043888","NCT00043953","NCT00050895","NCT00074581","NCT00078247","NCT00082394","NCT00084136","NCT00084149","NCT00086359","NCT00099359","NCT00099632","NCT00102206","NCT00102960","NCT00104429","NCT00109590","NCT00112047","NCT00115648","NCT00142337","NCT00143689","NCT00146380","NCT00158405","NCT00164736","NCT00167674","NCT00199121","NCT00234091","NCT00234923","NCT00270296","NCT00273975","NCT00307151","NCT00335322","NCT00342355","NCT00385957","NCT00386230","NCT00389194","NCT00405925","NCT00409591","NCT00424814"]}],"maxPhaseForIndication":4},{"disease":"MONDO_0021094","efoName":"immunodeficiency disease","references":[{"source":"DailyMed","ids":["6df09f15-b102-431c-adde-d7aeef6f5d84","1bc4c6c8-7e75-494e-810b-8f83135a3204","9b32f5a4-d0f7-486b-b699-8dc9202b6869"]}],"maxPhaseForIndication":4},{"disease":"EFO_1001486","efoName":"primary biliary cirrhosis","references":[{"source":"ClinicalTrials","ids":["NCT00490620"]}],"maxPhaseForIndication":2},{"disease":"EFO_0000544","efoName":"infection","references":[{"source":"ClinicalTrials","ids":["NCT02150993"]}],"maxPhaseForIndication":2}],"approvedIndications":["MONDO_0021094","EFO_0000764","EFO_0000180","EFO_0000763"],"indicationCount":21}
{"id":"CHEMBL2108720","indications":[{"disease":"MONDO_0004979","efoName":"asthma","references":[{"source":"ClinicalTrials","ids":["NCT00983658","NCT01152619"]}],"maxPhaseForIndication":2}],"approvedIndications":[],"indicationCount":1}
{"id":"CHEMBL891","indications":[{"disease":"EFO_1001313","efoName":"enterobacteriaceae infections","references":[{"source":"ClinicalTrials","ids":["NCT02795949"]}],"maxPhaseForIndication":3},{"disease":"EFO_0000771","efoName":"bacterial disease","references":[{"source":"ATC","ids":["J01CF02"]}],"maxPhaseForIndication":4},{"disease":"EFO_0003102","efoName":"osteomyelitis","references":[{"source":"ClinicalTrials","ids":["NCT02099240"]}],"maxPhaseForIndication":0},{"disease":"MONDO_0021679","efoName":"gram-positive bacterial infections","references":[{"source":"ClinicalTrials","ids":["NCT00062647"]}],"maxPhaseForIndication":2},{"disease":"EFO_1001034","efoName":"mastitis","references":[{"source":"ClinicalTrials","ids":["NCT00716183"]}],"maxPhaseForIndication":2},{"disease":"EFO_0005681","efoName":"staphylococcus aureus infection","references":[{"source":"ClinicalTrials","ids":["NCT01792804","NCT01875263"]}],"maxPhaseForIndication":3}],"approvedIndications":["EFO_0000771"],"indicationCount":6}
{"id":"CHEMBL1770248","indications":[{"disease":"EFO_0003144","efoName":"heart failure","references":[{"source":"ClinicalTrials","ids":["NCT04438213"]}],"maxPhaseForIndication":2},{"disease":"MONDO_0005148","efoName":"type 2 diabetes mellitus","references":[{"source":"FDA","ids":["label/2017/209803s000lbl.pdf"]},{"source":"ClinicalTrials","ids":["NCT00989079","NCT01054300","NCT01059825","NCT01127308","NCT01223339","NCT01958671","NCT01986855","NCT01986881","NCT01999218","NCT02033889","NCT02036515","NCT02099110","NCT02115347","NCT02226003","NCT02411929","NCT02630706","NCT04029480"]}],"maxPhaseForIndication":4},{"disease":"EFO_0000400","efoName":"diabetes mellitus","references":[{"source":"ATC","ids":["A10BK04"]}],"maxPhaseForIndication":4}],"approvedIndications":["MONDO_0005148","EFO_0000400"],"indicationCount":3}
{"id":"CHEMBL2109016","indications":[{"disease":"EFO_0004260","efoName":"bone disease","references":[{"source":"ATC","ids":["M05BX02"]}],"maxPhaseForIndication":4},{"disease":"MONDO_0002406","efoName":"dermatitis","references":[{"source":"DailyMed","ids":["4aa71dc9-39fd-63a2-e054-00144ff88e88"]}],"maxPhaseForIndication":4},{"disease":"EFO_0003086","efoName":"kidney disease","references":[{"source":"DailyMed","ids":["669a0555-38ad-42de-820d-abcb70982845"]}],"maxPhaseForIndication":4}],"approvedIndications":["EFO_0003086","MONDO_0002406","EFO_0004260"],"indicationCount":3}
{"id":"CHEMBL2109152","indications":[{"disease":"EFO_0000701","efoName":"skin disease","references":[{"source":"ClinicalTrials","ids":["NCT02379793"]}],"maxPhaseForIndication":1},{"disease":"MONDO_0002203","efoName":"constipation disorder","references":[{"source":"DailyMed","ids":["1589ff26-ad82-4520-bd39-f5d5a9c165eb"]}],"maxPhaseForIndication":4},{"disease":"HP_0002019","efoName":"constipation","references":[{"source":"ATC","ids":["A06AA01","A06AA51"]}],"maxPhaseForIndication":4}],"approvedIndications":["HP_0002019","MONDO_0002203"],"indicationCount":3}
{"id":"CHEMBL2108292","indications":[{"disease":"Orphanet_98879","efoName":"hemophilia b","references":[{"source":"ClinicalTrials","ids":["NCT00922792"]}],"maxPhaseForIndication":1},{"disease":"Orphanet_98878","efoName":"hemophilia a","references":[{"source":"ClinicalTrials","ids":["NCT00922792"]}],"maxPhaseForIndication":1}],"approvedIndications":[],"indicationCount":2}
{"id":"CHEMBL4297537","indications":[{"disease":"EFO_0009562","efoName":"polyneuropathy","references":[{"source":"DailyMed","ids":["8513207e-b55f-417b-9473-af785146a543"]}],"maxPhaseForIndication":4},{"disease":"Orphanet_85447","efoName":"familial amyloid polyneuropathy","references":[{"source":"FDA","ids":["label/2018/211172lbl.pdf"]}],"maxPhaseForIndication":4},{"disease":"EFO_1001875","efoName":"amyloidosis","references":[{"source":"DailyMed","ids":["8513207e-b55f-417b-9473-af785146a543"]}],"maxPhaseForIndication":4}],"approvedIndications":["EFO_0009562","EFO_1001875","Orphanet_85447"],"indicationCount":3}
{"id":"CHEMBL33720","indications":[{"disease":"EFO_0005751","efoName":"eye allergy","references":[{"source":"ATC","ids":["S01GA06","S01GA56"]}],"maxPhaseForIndication":0},{"disease":"EFO_0000319","efoName":"cardiovascular disease","references":[{"source":"ATC","ids":["C01CA08"]}],"maxPhaseForIndication":0}],"approvedIndications":[],"indicationCount":2}
{"id":"CHEMBL1201608","indications":[{"disease":"EFO_0000389","efoName":"cutaneous melanoma","references":[{"source":"ClinicalTrials","ids":["NCT00004022"]}],"maxPhaseForIndication":2},{"disease":"EFO_0003865","efoName":"kidney neoplasm","references":[{"source":"ClinicalTrials","ids":["NCT00091611"]}],"maxPhaseForIndication":2},{"disease":"EFO_1001249","efoName":"non-alcoholic steatohepatitis","references":[{"source":"ClinicalTrials","ids":["NCT01205087"]}],"maxPhaseForIndication":2},{"disease":"EFO_0000616","efoName":"neoplasm","references":[{"source":"ClinicalTrials","ids":["NCT00002482"]}],"maxPhaseForIndication":1},{"disease":"EFO_0000540","efoName":"immune system disease","references":[{"source":"ATC","ids":["L04AA02"]}],"maxPhaseForIndication":4},{"disease":"EFO_0000311","efoName":"cancer","references":[{"source":"ClinicalTrials","ids":["NCT00202917","NCT00824135"]}],"maxPhaseForIndication":1},{"disease":"EFO_0000729","efoName":"ulcerative colitis","references":[{"source":"ClinicalTrials","ids":["NCT01287195"]}],"maxPhaseForIndication":1},{"disease":"EFO_0000756","efoName":"melanoma","references":[{"source":"ClinicalTrials","ids":["NCT00080353"]}],"maxPhaseForIndication":2},{"disease":"EFO_1000158","efoName":"central nervous system neoplasm","references":[{"source":"ClinicalTrials","ids":["NCT00002572","NCT00004024"]}],"maxPhaseForIndication":2},{"disease":"MONDO_0002367","efoName":"kidney cancer","references":[{"source":"ClinicalTrials","ids":["NCT00002589"]}],"maxPhaseForIndication":2}],"approvedIndications":["EFO_0000540"],"indicationCount":10}
{"id":"CHEMBL1194","indications":[{"disease":"EFO_0000707","efoName":"squamous cell carcinoma","references":[{"source":"ClinicalTrials","ids":["NCT02666534"]}],"maxPhaseForIndication":1},{"disease":"EFO_0002496","efoName":"actinic keratosis","references":[{"source":"ClinicalTrials","ids":["NCT02670655"]}],"maxPhaseForIndication":1},{"disease":"EFO_0003843","efoName":"pain","references":[{"source":"DailyMed","ids":["e9fdb9c9-fd00-443d-acc4-516fa8265c00","2a9976e3-4595-4bc5-b7f9-f4a9bd59e55d","3e1cfe73-1d7f-4807-a26d-0d4c2b4894d9","8debb03e-a237-4e0d-be06-8ae17eaa14fa","b466c7eb-bca3-4686-ada6-325103ab06f3","b6c88c84-cd82-4390-aea5-b04f15f57143","9378d186-5b25-49bc-8563-a659fa1194c2","b61c6a09-7764-4a92-93a9-a1356aeeaa9c","823c2d42-d00d-401d-4081-fc1d434455e0","625c2437-2999-4b82-8331-51cd32aa3292","1972d657-2d5a-4697-bba9-80caffc2f2d7","c05f3803-92ae-42b7-8248-933bd92d6116","833cd52c-6470-49c4-937f-1393971f4db9","7bb482ba-632b-4d8f-a7d4-3fc857bdeef7"]},{"source":"ClinicalTrials","ids":["NCT00562211","NCT01094015","NCT02380742","NCT02519660","NCT02658773","NCT03264586","NCT03508804","NCT04784104"]}],"maxPhaseForIndication":4},{"disease":"EFO_0002950","efoName":"pregnancy","references":[{"source":"ClinicalTrials","ids":["NCT03036384"]}],"maxPhaseForIndication":2},{"disease":"EFO_0000701","efoName":"skin disease","references":[{"source":"ClinicalTrials","ids":["NCT04523961"]}],"maxPhaseForIndication":2},{"disease":"MONDO_0041052","efoName":"postherpetic neuralgia","references":[{"source":"ClinicalTrials","ids":["NCT00916942"]}],"maxPhaseForIndication":2}],"approvedIndications":["EFO_0003843"],"indicationCount":6}
{"id":"CHEMBL3991932","indications":[{"disease":"EFO_0000198","efoName":"myelodysplastic syndrome","references":[{"source":"ClinicalTrials","ids":["NCT00916227","NCT01496495"]}],"maxPhaseForIndication":1}],"approvedIndications":[],"indicationCount":1}
{"id":"CHEMBL3769414","indications":[{"disease":"EFO_1001207","efoName":"systolic heart failure","references":[{"source":"ClinicalTrials","ids":["NCT03387215"]}],"maxPhaseForIndication":1},{"disease":"MONDO_0005090","efoName":"schizophrenia","references":[{"source":"ClinicalTrials","ids":["NCT01900522"]}],"maxPhaseForIndication":1},{"disease":"MONDO_0005180","efoName":"parkinson disease","references":[{"source":"ClinicalTrials","ids":["NCT03257046"]}],"maxPhaseForIndication":1}],"approvedIndications":[],"indicationCount":3}
{"id":"CHEMBL4297460","indications":[{"disease":"Orphanet_3389","efoName":"tuberculosis","references":[{"source":"ClinicalTrials","ids":["NCT02968927"]}],"maxPhaseForIndication":2},{"disease":"EFO_0003834","efoName":"cutaneous lupus erythematosus","references":[{"source":"ClinicalTrials","ids":["NCT01300208"]}],"maxPhaseForIndication":2}],"approvedIndications":[],"indicationCount":2}
{"id":"CHEMBL2105953","indications":[{"disease":"EFO_0000771","efoName":"bacterial disease","references":[{"source":"ATC","ids":["J01DD18"]}],"maxPhaseForIndication":0}],"approvedIndications":[],"indicationCount":1}
{"id":"CHEMBL3544989","indications":[{"disease":"EFO_1000727","efoName":"lipodystrophy","references":[{"source":"ClinicalTrials","ids":["NCT02639286"]}],"maxPhaseForIndication":2}],"approvedIndications":[],"indicationCount":1}
{"id":"CHEMBL3544952","indications":[{"disease":"MONDO_0004975","efoName":"alzheimer disease","references":[{"source":"ClinicalTrials","ids":["NCT00454870"]}],"maxPhaseForIndication":2},{"disease":"MONDO_0005090","efoName":"schizophrenia","references":[{"source":"ClinicalTrials","ids":["NCT00725855"]}],"maxPhaseForIndication":2}],"approvedIndications":[],"indicationCount":2}
{"id":"CHEMBL4094396","indications":[{"disease":"EFO_0004701","efoName":"methamphetamine dependence","references":[{"source":"ClinicalTrials","ids":["NCT02232789"]}],"maxPhaseForIndication":1}],"approvedIndications":[],"indicationCount":1}
{"id":"CHEMBL2108609","indications":[{"disease":"MONDO_0008170","efoName":"ovarian cancer","references":[{"source":"ClinicalTrials","ids":["NCT00088413"]}],"maxPhaseForIndication":1},{"disease":"MONDO_0007254","efoName":"breast cancer","references":[{"source":"ClinicalTrials","ids":["NCT00088413","NCT00179309"]}],"maxPhaseForIndication":2},{"disease":"EFO_0000228","efoName":"adenocarcinoma","references":[{"source":"ClinicalTrials","ids":["NCT00088413"]}],"maxPhaseForIndication":1},{"disease":"EFO_1001951","efoName":"colorectal carcinoma","references":[{"source":"ClinicalTrials","ids":["NCT00088413"]}],"maxPhaseForIndication":1},{"disease":"MONDO_0001187","efoName":"urinary bladder cancer","references":[{"source":"ClinicalTrials","ids":["NCT02015104"]}],"maxPhaseForIndication":2}],"approvedIndications":[],"indicationCount":5}
{"id":"CHEMBL4650312","indications":[{"disease":"EFO_0000274","efoName":"atopic eczema","references":[{"source":"ClinicalTrials","ids":["NCT02795832"]}],"maxPhaseForIndication":1}],"approvedIndications":[],"indicationCount":1}
{"id":"CHEMBL1295","indications":[{"disease":"EFO_1001240","efoName":"vulvovaginitis","references":[{"source":"ClinicalTrials","ids":["NCT00616330"]}],"maxPhaseForIndication":3}],"approvedIndications":[],"indicationCount":1}
{"id":"CHEMBL1201325","indications":[{"disease":"EFO_0010282","efoName":"gastrointestinal disease","references":[{"source":"ATC","ids":["A03AB10"]}],"maxPhaseForIndication":4}],"approvedIndications":["EFO_0010282"],"indicationCount":1}
{"id":"CHEMBL2104988","indications":[{"disease":"EFO_0008507","efoName":"interstitial cystitis","references":[{"source":"ClinicalTrials","ids":["NCT00295854"]}],"maxPhaseForIndication":2},{"disease":"EFO_0000768","efoName":"idiopathic pulmonary fibrosis","references":[{"source":"ClinicalTrials","ids":["NCT02503657"]}],"maxPhaseForIndication":2},{"disease":"EFO_0004211","efoName":"hypertriglyceridemia","references":[{"source":"ClinicalTrials","ids":["NCT02681055"]}],"maxPhaseForIndication":2}],"approvedIndications":[],"indicationCount":3}
{"id":"CHEMBL1201759","indications":[{"disease":"HP_0000989","efoName":"pruritus","references":[{"source":"ClinicalTrials","ids":["NCT03317301"]},{"source":"DailyMed","ids":["68bbf6a0-c4b5-47c1-8a1c-08220fbdbce6"]}],"maxPhaseForIndication":4},{"disease":"EFO_1001417","efoName":"rhinitis, allergic, perennial","references":[{"source":"ClinicalTrials","ids":["NCT01425632","NCT02682745","NCT02686294"]}],"maxPhaseForIndication":3},{"disease":"EFO_0007141","efoName":"allergic conjunctivitis","references":[{"source":"DailyMed","ids":["68bbf6a0-c4b5-47c1-8a1c-08220fbdbce6"]},{"source":"ClinicalTrials","ids":["NCT00424398","NCT00586625","NCT01346371"]}],"maxPhaseForIndication":4}],"approvedIndications":["HP_0000989","EFO_0007141"],"indicationCount":3}
{"id":"CHEMBL2386889","indications":[{"disease":"EFO_0000183","efoName":"hodgkins lymphoma","references":[{"source":"ClinicalTrials","ids":["NCT00779584"]}],"maxPhaseForIndication":1},{"disease":"EFO_0000222","efoName":"acute myeloid leukemia","references":[{"source":"ClinicalTrials","ids":["NCT00907517"]}],"maxPhaseForIndication":1},{"disease":"EFO_0000339","efoName":"chronic myelogenous leukemia","references":[{"source":"ClinicalTrials","ids":["NCT00907517"]}],"maxPhaseForIndication":1},{"disease":"EFO_0005952","efoName":"non-hodgkins lymphoma","references":[{"source":"ClinicalTrials","ids":["NCT00779584"]}],"maxPhaseForIndication":1},{"disease":"EFO_0000220","efoName":"acute lymphoblastic leukemia","references":[{"source":"ClinicalTrials","ids":["NCT00907517"]}],"maxPhaseForIndication":1}],"approvedIndications":[],"indicationCount":5}
{"id":"CHEMBL4650298","indications":[{"disease":"EFO_0003060","efoName":"non-small cell lung carcinoma","references":[{"source":"ClinicalTrials","ids":["NCT03130881"]}],"maxPhaseForIndication":1}],"approvedIndications":[],"indicationCount":1}
{"id":"CHEMBL345714","indications":[{"disease":"EFO_0005204","efoName":"bulimia nervosa","references":[{"source":"ClinicalTrials","ids":["NCT03338387"]}],"maxPhaseForIndication":2},{"disease":"MONDO_0005148","efoName":"type 2 diabetes mellitus","references":[{"source":"ClinicalTrials","ids":["NCT00153179","NCT01980524"]}],"maxPhaseForIndication":2},{"disease":"MONDO_0005147","efoName":"type 1 diabetes mellitus","references":[{"source":"ClinicalTrials","ids":["NCT01816165"]}],"maxPhaseForIndication":3},{"disease":"EFO_0000195","efoName":"metabolic syndrome","references":[{"source":"ClinicalTrials","ids":["NCT00759291"]}],"maxPhaseForIndication":2},{"disease":"EFO_0003144","efoName":"heart failure","references":[{"source":"ClinicalTrials","ids":["NCT00449423"]}],"maxPhaseForIndication":2}],"approvedIndications":[],"indicationCount":5}
{"id":"CHEMBL223402","indications":[{"disease":"EFO_1001413","efoName":"respiratory syncytial virus infection","references":[{"source":"ClinicalTrials","ids":["NCT00232635"]}],"maxPhaseForIndication":2}],"approvedIndications":[],"indicationCount":1}
{"id":"CHEMBL3137303","indications":[{"disease":"EFO_0000220","efoName":"acute lymphoblastic leukemia","references":[{"source":"ClinicalTrials","ids":["NCT01049113"]}],"maxPhaseForIndication":1}],"approvedIndications":[],"indicationCount":1}
{"id":"CHEMBL4594309","indications":[{"disease":"EFO_0001378","efoName":"multiple myeloma","references":[{"source":"ClinicalTrials","ids":["NCT03430011"]}],"maxPhaseForIndication":1}],"approvedIndications":[],"indicationCount":1}
{"id":"CHEMBL178459","indications":[{"disease":"EFO_0001422","efoName":"cirrhosis of liver","references":[{"source":"ClinicalTrials","ids":["NCT00956098"]}],"maxPhaseForIndication":2},{"disease":"MONDO_0008903","efoName":"lung cancer","references":[{"source":"ClinicalTrials","ids":["NCT00006457"]}],"maxPhaseForIndication":1},{"disease":"EFO_0003095","efoName":"non-alcoholic fatty liver disease","references":[{"source":"ClinicalTrials","ids":["NCT01373554","NCT02068339","NCT04142749"]}],"maxPhaseForIndication":3}],"approvedIndications":[],"indicationCount":3}
{"id":"CHEMBL47298","indications":[{"disease":"EFO_0000763","efoName":"viral disease","references":[{"source":"ATC","ids":["J05AX19"]}],"maxPhaseForIndication":0}],"approvedIndications":[],"indicationCount":1}
{"id":"CHEMBL191482","indications":[{"disease":"EFO_0001378","efoName":"multiple myeloma","references":[{"source":"ClinicalTrials","ids":["NCT02569320"]}],"maxPhaseForIndication":1}],"approvedIndications":[],"indicationCount":1}
{"id":"CHEMBL1828820","indications":[{"disease":"EFO_0007444","efoName":"plasmodium falciparum malaria","references":[{"source":"ClinicalTrials","ids":["NCT01213966","NCT02497612","NCT03660839"]}],"maxPhaseForIndication":2},{"disease":"EFO_0007530","efoName":"urinary schistosomiasis","references":[{"source":"ClinicalTrials","ids":["NCT04264130"]}],"maxPhaseForIndication":2},{"disease":"EFO_0007445","efoName":"plasmodium vivax malaria","references":[{"source":"ClinicalTrials","ids":["NCT01213966"]}],"maxPhaseForIndication":2},{"disease":"EFO_0001068","efoName":"malaria","references":[{"source":"ClinicalTrials","ids":["NCT01615822","NCT01713608","NCT01713621","NCT01853475","NCT01958619","NCT02083406","NCT02387580","NCT02389348","NCT02431650","NCT02453581","NCT02573857","NCT04069221"]}],"maxPhaseForIndication":2}],"approvedIndications":[],"indicationCount":4}
{"id":"CHEMBL559362","indications":[{"disease":"EFO_0000616","efoName":"neoplasm","references":[{"source":"ClinicalTrials","ids":["NCT00027677"]}],"maxPhaseForIndication":1},{"disease":"EFO_0000558","efoName":"kaposi's sarcoma","references":[{"source":"ClinicalTrials","ids":["NCT00064142"]}],"maxPhaseForIndication":2}],"approvedIndications":[],"indicationCount":2}
{"id":"CHEMBL190412","indications":[{"disease":"EFO_0000574","efoName":"lymphoma","references":[{"source":"ClinicalTrials","ids":["NCT00457574"]}],"maxPhaseForIndication":1}],"approvedIndications":[],"indicationCount":1}
{"id":"CHEMBL447955","indications":[{"disease":"HP_0000989","efoName":"pruritus","references":[{"source":"ClinicalTrials","ids":["NCT01951274","NCT03841331"]}],"maxPhaseForIndication":2},{"disease":"EFO_1000690","efoName":"epidermolysis bullosa","references":[{"source":"ClinicalTrials","ids":["NCT03836001"]}],"maxPhaseForIndication":2}],"approvedIndications":[],"indicationCount":2}
{"id":"CHEMBL289480","indications":[{"disease":"EFO_0000537","efoName":"hypertension","references":[{"source":"ATC","ids":["C02AC06"]}],"maxPhaseForIndication":3}],"approvedIndications":[],"indicationCount":1}
{"id":"CHEMBL4297501","indications":[{"disease":"EFO_0000544","efoName":"infection","references":[{"source":"ClinicalTrials","ids":["NCT03723551"]}],"maxPhaseForIndication":2}],"approvedIndications":[],"indicationCount":1}
{"id":"CHEMBL4298191","indications":[{"disease":"MONDO_0001187","efoName":"urinary bladder cancer","references":[{"source":"ClinicalTrials","ids":["NCT04165317"]}],"maxPhaseForIndication":3},{"disease":"EFO_0003060","efoName":"non-small cell lung carcinoma","references":[{"source":"ClinicalTrials","ids":["NCT04181788","NCT04585815"]}],"maxPhaseForIndication":2},{"disease":"EFO_0000673","efoName":"prostate adenocarcinoma","references":[{"source":"ClinicalTrials","ids":["NCT02616185"]}],"maxPhaseForIndication":1}],"approvedIndications":[],"indicationCount":3}
{"id":"CHEMBL46730","indications":[{"disease":"EFO_0003768","efoName":"nicotine dependence","references":[{"source":"ClinicalTrials","ids":["NCT01092650","NCT02999399"]}],"maxPhaseForIndication":1}],"approvedIndications":[],"indicationCount":1}
{"id":"CHEMBL3545007","indications":[{"disease":"EFO_0000616","efoName":"neoplasm","references":[{"source":"ClinicalTrials","ids":["NCT01359696"]}],"maxPhaseForIndication":1}],"approvedIndications":[],"indicationCount":1}
{"id":"CHEMBL4297830","indications":[{"disease":"EFO_1001109","efoName":"pituitary dwarfism","references":[{"source":"ClinicalTrials","ids":["NCT02418767","NCT03831880","NCT03874013"]}],"maxPhaseForIndication":3}],"approvedIndications":[],"indicationCount":1}
{"id":"CHEMBL4298119","indications":[{"disease":"MONDO_0007254","efoName":"breast cancer","references":[{"source":"ClinicalTrials","ids":["NCT03720431"]}],"maxPhaseForIndication":1},{"disease":"EFO_0000519","efoName":"glioblastoma multiforme","references":[{"source":"ClinicalTrials","ids":["NCT03033524","NCT03722342","NCT03856099"]}],"maxPhaseForIndication":2}],"approvedIndications":[],"indicationCount":2}
{"id":"CHEMBL4594565","indications":[{"disease":"Orphanet_79213","efoName":"mucopolysaccharidosis","references":[{"source":"ClinicalTrials","ids":["NCT03128593","NCT03359213","NCT03568175","NCT03708965","NCT04348136","NCT04573023"]}],"maxPhaseForIndication":3}],"approvedIndications":[],"indicationCount":1}
{"id":"CHEMBL4297958","indications":[{"disease":"MONDO_0015183","efoName":"short bowel syndrome","references":[{"source":"ClinicalTrials","ids":["NCT01573286","NCT03415594"]}],"maxPhaseForIndication":1},{"disease":"Orphanet_309005","efoName":"disorder of lipid metabolism","references":[{"source":"ClinicalTrials","ids":["NCT01958775"]}],"maxPhaseForIndication":3}],"approvedIndications":[],"indicationCount":2}
{"id":"CHEMBL435128","indications":[{"disease":"EFO_0000764","efoName":"hiv infection","references":[{"source":"ClinicalTrials","ids":["NCT00002214","NCT00004985","NCT00004998","NCT00004999","NCT00005673","NCT00006211","NCT00006519","NCT00051844","NCT00052117"]}],"maxPhaseForIndication":2}],"approvedIndications":[],"indicationCount":1}
{"id":"CHEMBL2110731","indications":[{"disease":"MONDO_0005148","efoName":"type 2 diabetes mellitus","references":[{"source":"ClinicalTrials","ids":["NCT00682097","NCT00800176","NCT00933972","NCT01044017"]}],"maxPhaseForIndication":2}],"approvedIndications":[],"indicationCount":1}
{"id":"CHEMBL278519","indications":[{"disease":"HP_0004419","efoName":"recurrent thrombophlebitis","references":[{"source":"ATC","ids":["B01AA09"]}],"maxPhaseForIndication":0}],"approvedIndications":[],"indicationCount":1}
{"id":"CHEMBL1373254","indications":[{"disease":"EFO_0000319","efoName":"cardiovascular disease","references":[{"source":"ATC","ids":["C03AA07"]}],"maxPhaseForIndication":4}],"approvedIndications":["EFO_0000319"],"indicationCount":1}
{"id":"CHEMBL2107583","indications":[{"disease":"EFO_0000319","efoName":"cardiovascular disease","references":[{"source":"ATC","ids":["C01DA63","C01DA13"]}],"maxPhaseForIndication":0}],"approvedIndications":[],"indicationCount":1}
{"id":"CHEMBL1200351","indications":[{"disease":"EFO_0001068","efoName":"malaria","references":[{"source":"DailyMed","ids":["10549cba-9c15-4d2e-a68c-5afbc178591d"]}],"maxPhaseForIndication":4}],"approvedIndications":["EFO_0001068"],"indicationCount":1}
