{"id":"CHEMBL109480","indications":[{"disease":"MONDO_0018906","efoName":"follicular lymphoma","references":[{"source":"ClinicalTrials","ids":["NCT00004241","NCT00096005"]}],"maxPhaseForIndication":1},{"disease":"MONDO_0019471","efoName":"adult t-cell leukemia/lymphoma","references":[{"source":"ClinicalTrials","ids":["NCT00004241","NCT00096005"]}],"maxPhaseForIndication":1},{"disease":"EFO_0009441","efoName":"waldenstrom macroglobulinemia","references":[{"source":"ClinicalTrials","ids":["NCT00096005"]}],"maxPhaseForIndication":1},{"disease":"MONDO_0008903","efoName":"lung cancer","references":[{"source":"ClinicalTrials","ids":["NCT00004065"]}],"maxPhaseForIndication":1},{"disease":"MONDO_0007254","efoName":"breast cancer","references":[{"source":"ClinicalTrials","ids":["NCT00004065","NCT00096109","NCT00773344"]}],"maxPhaseForIndication":2},{"disease":"EFO_1000785","efoName":"sezary's disease","references":[{"source":"ClinicalTrials","ids":["NCT00004241","NCT00096005"]}],"maxPhaseForIndication":1},{"disease":"EFO_0000637","efoName":"osteosarcoma","references":[{"source":"ClinicalTrials","ids":["NCT00004241"]}],"maxPhaseForIndication":1},{"disease":"EFO_0000403","efoName":"diffuse large b-cell lymphoma","references":[{"source":"ClinicalTrials","ids":["NCT00004241","NCT00096005"]}],"maxPhaseForIndication":1},{"disease":"MONDO_0015277","efoName":"medullary thyroid gland carcinoma","references":[{"source":"ClinicalTrials","ids":["NCT00118248"]}],"maxPhaseForIndication":2},{"disease":"EFO_0000673","efoName":"prostate adenocarcinoma","references":[{"source":"ClinicalTrials","ids":["NCT00118092"]}],"maxPhaseForIndication":2},{"disease":"EFO_0000183","efoName":"hodgkins lymphoma","references":[{"source":"ClinicalTrials","ids":["NCT00004241","NCT00096005","NCT00117988"]}],"maxPhaseForIndication":2},{"disease":"MONDO_0008170","efoName":"ovarian cancer","references":[{"source":"ClinicalTrials","ids":["NCT00004065"]}],"maxPhaseForIndication":1},{"disease":"EFO_0000311","efoName":"cancer","references":[{"source":"ClinicalTrials","ids":["NCT00779428"]}],"maxPhaseForIndication":2},{"disease":"EFO_0000574","efoName":"lymphoma","references":[{"source":"ClinicalTrials","ids":["NCT00004075"]}],"maxPhaseForIndication":1},{"disease":"EFO_0000756","efoName":"melanoma","references":[{"source":"ClinicalTrials","ids":["NCT00087386"]}],"maxPhaseForIndication":2},{"disease":"EFO_0000565","efoName":"leukemia","references":[{"source":"ClinicalTrials","ids":["NCT00004065","NCT00066326","NCT00100997"]}],"maxPhaseForIndication":1},{"disease":"EFO_1001365","efoName":"lymphoma, aids-related","references":[{"source":"ClinicalTrials","ids":["NCT00004241","NCT00096005"]}],"maxPhaseForIndication":1},{"disease":"EFO_0000309","efoName":"burkitts lymphoma","references":[{"source":"ClinicalTrials","ids":["NCT00004241","NCT00096005"]}],"maxPhaseForIndication":1},{"disease":"MONDO_0001023","efoName":"prolymphocytic leukemia","references":[{"source":"ClinicalTrials","ids":["NCT00098488"]}],"maxPhaseForIndication":1},{"disease":"EFO_0002428","efoName":"chronic myeloproliferative disorder","references":[{"source":"ClinicalTrials","ids":["NCT00132015"]}],"maxPhaseForIndication":2},{"disease":"EFO_0000191","efoName":"malt lymphoma","references":[{"source":"ClinicalTrials","ids":["NCT00096005"]}],"maxPhaseForIndication":1},{"disease":"MONDO_0002367","efoName":"kidney cancer","references":[{"source":"ClinicalTrials","ids":["NCT00004065","NCT00093405"]}],"maxPhaseForIndication":2},{"disease":"EFO_0006859","efoName":"head and neck malignant neoplasia","references":[{"source":"ClinicalTrials","ids":["NCT00004065"]}],"maxPhaseForIndication":1},{"disease":"EFO_0003032","efoName":"anaplastic large cell lymphoma","references":[{"source":"ClinicalTrials","ids":["NCT00004241","NCT00096005","NCT00117988"]}],"maxPhaseForIndication":2},{"disease":"EFO_0000641","efoName":"papillary thyroid carcinoma","references":[{"source":"ClinicalTrials","ids":["NCT00118248"]}],"maxPhaseForIndication":2},{"disease":"EFO_0000255","efoName":"angioimmunoblastic t-cell lymphoma","references":[{"source":"ClinicalTrials","ids":["NCT00004241","NCT00096005"]}],"maxPhaseForIndication":1},{"disease":"EFO_0001378","efoName":"multiple myeloma","references":[{"source":"ClinicalTrials","ids":["NCT00514371","NCT00546780"]}],"maxPhaseForIndication":3},{"disease":"EFO_0000333","efoName":"chondrosarcoma","references":[{"source":"ClinicalTrials","ids":["NCT00004241"]}],"maxPhaseForIndication":1},{"disease":"EFO_0000616","efoName":"neoplasm","references":[{"source":"ClinicalTrials","ids":["NCT00003969","NCT00047047","NCT00087217","NCT00119236","NCT00121264"]}],"maxPhaseForIndication":2},{"disease":"EFO_1001051","efoName":"mycosis fungoides","references":[{"source":"ClinicalTrials","ids":["NCT00004241","NCT00096005"]}],"maxPhaseForIndication":1},{"disease":"MONDO_0000873","efoName":"lymphoblastic lymphoma","references":[{"source":"ClinicalTrials","ids":["NCT00004241","NCT00096005"]}],"maxPhaseForIndication":1},{"disease":"EFO_1001951","efoName":"colorectal carcinoma","references":[{"source":"ClinicalTrials","ids":["NCT00004065"]}],"maxPhaseForIndication":1},{"disease":"MONDO_0001187","efoName":"urinary bladder cancer","references":[{"source":"ClinicalTrials","ids":["NCT00004065"]}],"maxPhaseForIndication":1},{"disease":"EFO_1001469","efoName":"mantle cell lymphoma","references":[{"source":"ClinicalTrials","ids":["NCT00004241","NCT00096005","NCT00117988"]}],"maxPhaseForIndication":2},{"disease":"MONDO_0008315","efoName":"prostate cancer","references":[{"source":"ClinicalTrials","ids":["NCT00004065","NCT00058253"]}],"maxPhaseForIndication":1},{"disease":"MONDO_0001056","efoName":"gastric cancer","references":[{"source":"ClinicalTrials","ids":["NCT00004065"]}],"maxPhaseForIndication":1},{"disease":"EFO_0000095","efoName":"chronic lymphocytic leukemia","references":[{"source":"ClinicalTrials","ids":["NCT00004241","NCT00096005","NCT00098488","NCT00319930"]}],"maxPhaseForIndication":1},{"disease":"EFO_0000389","efoName":"cutaneous melanoma","references":[{"source":"ClinicalTrials","ids":["NCT00004065","NCT00104897"]}],"maxPhaseForIndication":2}],"approvedIndications":[],"indicationCount":38}
{"id":"CHEMBL1072","indications":[{"disease":"MONDO_0005148","efoName":"type 2 diabetes mellitus","references":[{"source":"ClinicalTrials","ids":["NCT00930865"]}],"maxPhaseForIndication":1},{"disease":"EFO_0003144","efoName":"heart failure","references":[{"source":"ClinicalTrials","ids":["NCT00372762"]}],"maxPhaseForIndication":4},{"disease":"EFO_0000319","efoName":"cardiovascular disease","references":[{"source":"ATC","ids":["C03CA02"]}],"maxPhaseForIndication":4},{"disease":"EFO_0004255","efoName":"nephrotic syndrome","references":[{"source":"DailyMed","ids":["925b309a-8a0b-4bcd-bdf4-1ec42780ecc2","b5a68154-8003-4b80-81e2-e926524fb72c","c386547a-e741-4dee-84f4-f520ea895291","d91945d7-f626-4ae2-b252-c88a38fc9ca1","0fb6d547-9966-4352-8974-d02ea58e6445","cf01d206-f19e-4ab4-ac76-2a1297dced72","509dba6d-7e53-02ed-8d86-fe83a2126250","1c4015ba-567a-403c-91f6-fad7749ea2a2","f5e9dc4f-3b0b-4b2e-ace4-abe1d1989768","e71daa68-2744-47da-64b4-0a725c2e8457","00b71dc2-1851-4670-a48e-b4eb89d48d0b","681b5e9d-e2c7-4f29-aaad-e06d4a528c11","fc35f3c6-a8c4-4cb7-8188-8269cc24cad8","c2e1f993-434a-4f09-acf0-a3849957d5c5","168fe885-a19e-4007-a258-77b50b22bfb4","a3594e64-c819-4b01-a7b2-ddacbda19ada","05cb961d-ac33-4bcf-b04e-411e496c43c1","c35aea66-17c7-47f5-8105-c33a53a26d5e","bf9ff69a-3436-41c8-b6a2-749f041daf4b","d788f9e9-105c-497d-8004-ac8ce80aee64","9d1b82df-9e2f-4ac4-99ed-f109228dac52","04236576-01c4-43a6-ac8a-60e23b5dc692"]},{"source":"FDA","ids":["label/2010/018225s024lbl.pdf"]}],"maxPhaseForIndication":4},{"disease":"EFO_0003086","efoName":"kidney disease","references":[{"source":"DailyMed","ids":["925b309a-8a0b-4bcd-bdf4-1ec42780ecc2","b5a68154-8003-4b80-81e2-e926524fb72c","c386547a-e741-4dee-84f4-f520ea895291","d91945d7-f626-4ae2-b252-c88a38fc9ca1","0fb6d547-9966-4352-8974-d02ea58e6445","cf01d206-f19e-4ab4-ac76-2a1297dced72","509dba6d-7e53-02ed-8d86-fe83a2126250","1c4015ba-567a-403c-91f6-fad7749ea2a2","f5e9dc4f-3b0b-4b2e-ace4-abe1d1989768","e71daa68-2744-47da-64b4-0a725c2e8457","00b71dc2-1851-4670-a48e-b4eb89d48d0b","681b5e9d-e2c7-4f29-aaad-e06d4a528c11","fc35f3c6-a8c4-4cb7-8188-8269cc24cad8","c2e1f993-434a-4f09-acf0-a3849957d5c5","168fe885-a19e-4007-a258-77b50b22bfb4","a3594e64-c819-4b01-a7b2-ddacbda19ada","05cb961d-ac33-4bcf-b04e-411e496c43c1","c35aea66-17c7-47f5-8105-c33a53a26d5e","bf9ff69a-3436-41c8-b6a2-749f041daf4b","d788f9e9-105c-497d-8004-ac8ce80aee64","9d1b82df-9e2f-4ac4-99ed-f109228dac52","04236576-01c4-43a6-ac8a-60e23b5dc692"]},{"source":"FDA","ids":["label/2010/018225s024lbl.pdf"]}],"maxPhaseForIndication":4},{"disease":"EFO_0003758","efoName":"autism","references":[{"source":"ClinicalTrials","ids":["NCT02947880","NCT04766177"]}],"maxPhaseForIndication":3},{"disease":"EFO_0003884","efoName":"chronic kidney disease","references":[{"source":"ClinicalTrials","ids":["NCT03923933"]}],"maxPhaseForIndication":2},{"disease":"Orphanet_681","efoName":"hypokalemic periodic paralysis","references":[{"source":"ClinicalTrials","ids":["NCT02582476"]}],"maxPhaseForIndication":2},{"disease":"HP_0001250","efoName":"seizure","references":[{"source":"ClinicalTrials","ids":["NCT00830531","NCT01434225"]}],"maxPhaseForIndication":1},{"disease":"EFO_0000182","efoName":"hepatocellular carcinoma","references":[{"source":"ClinicalTrials","ids":["NCT03107416"]}],"maxPhaseForIndication":1},{"disease":"EFO_0003756","efoName":"autism spectrum disorder","references":[{"source":"ClinicalTrials","ids":["NCT03156153"]}],"maxPhaseForIndication":2},{"disease":"EFO_0000373","efoName":"congestive heart failure","references":[{"source":"DailyMed","ids":["925b309a-8a0b-4bcd-bdf4-1ec42780ecc2","b5a68154-8003-4b80-81e2-e926524fb72c","c386547a-e741-4dee-84f4-f520ea895291","d91945d7-f626-4ae2-b252-c88a38fc9ca1","0fb6d547-9966-4352-8974-d02ea58e6445","cf01d206-f19e-4ab4-ac76-2a1297dced72","509dba6d-7e53-02ed-8d86-fe83a2126250","1c4015ba-567a-403c-91f6-fad7749ea2a2","f5e9dc4f-3b0b-4b2e-ace4-abe1d1989768","e71daa68-2744-47da-64b4-0a725c2e8457","00b71dc2-1851-4670-a48e-b4eb89d48d0b","681b5e9d-e2c7-4f29-aaad-e06d4a528c11","fc35f3c6-a8c4-4cb7-8188-8269cc24cad8","c2e1f993-434a-4f09-acf0-a3849957d5c5","168fe885-a19e-4007-a258-77b50b22bfb4","a3594e64-c819-4b01-a7b2-ddacbda19ada","05cb961d-ac33-4bcf-b04e-411e496c43c1","c35aea66-17c7-47f5-8105-c33a53a26d5e","bf9ff69a-3436-41c8-b6a2-749f041daf4b","d788f9e9-105c-497d-8004-ac8ce80aee64","9d1b82df-9e2f-4ac4-99ed-f109228dac52","04236576-01c4-43a6-ac8a-60e23b5dc692"]},{"source":"FDA","ids":["label/2010/018225s024lbl.pdf"]}],"maxPhaseForIndication":4}],"approvedIndications":["EFO_0003086","EFO_0003144","EFO_0004255","EFO_0000373","EFO_0000319"],"indicationCount":12}
{"id":"CHEMBL170","indications":[{"disease":"EFO_0009846","efoName":"muscle cramp","references":[{"source":"DailyMed","ids":["274650ff-90b2-4a2c-86a7-906c71b49280","1f66fba7-4026-4504-918d-4c88f2835cc0"]}],"maxPhaseForIndication":4},{"disease":"HP_0012532","efoName":"chronic pain","references":[{"source":"ClinicalTrials","ids":["NCT02276989"]}],"maxPhaseForIndication":2},{"disease":"EFO_0001068","efoName":"malaria","references":[{"source":"ATC","ids":["P01BC01"]},{"source":"ClinicalTrials","ids":["NCT00124267","NCT00167739","NCT00322907","NCT00329134","NCT00451139","NCT00495508","NCT00540202","NCT01374581","NCT01805232","NCT02492178","NCT02563704","NCT02974348"]}],"maxPhaseForIndication":4},{"disease":"EFO_0003086","efoName":"kidney disease","references":[{"source":"ClinicalTrials","ids":["NCT00785551"]}],"maxPhaseForIndication":1},{"disease":"EFO_0007444","efoName":"plasmodium falciparum malaria","references":[{"source":"ClinicalTrials","ids":["NCT00299208","NCT01047436","NCT01258049"]}],"maxPhaseForIndication":3},{"disease":"EFO_0007444","efoName":"plasmodium falciparum malaria","references":[{"source":"DailyMed","ids":["e782283e-2608-4fd6-a8b2-6c30b9d5d3b0","2c807aee-de5e-4523-8660-1611712efe7d","274650ff-90b2-4a2c-86a7-906c71b49280","1c44c8b7-8b38-4487-a8ba-a94f708d1f50","ce2ffee3-3048-43a0-ac45-ee32ce0c4c33","0b5bbefd-5b56-46f9-84f5-1456371577fd","1f66fba7-4026-4504-918d-4c88f2835cc0"]}],"maxPhaseForIndication":4},{"disease":"EFO_0001073","efoName":"obesity","references":[{"source":"ClinicalTrials","ids":["NCT04873011"]}],"maxPhaseForIndication":1}],"approvedIndications":["EFO_0007444","EFO_0001068","EFO_0009846"],"indicationCount":7}
{"id":"CHEMBL3184512","indications":[{"disease":"EFO_0003894","efoName":"acne","references":[{"source":"ATC","ids":["D10AF51"]},{"source":"DailyMed","ids":["fdd0e957-a600-40a3-b9c7-2b0fd98a5b12","697e760a-c206-4565-8f4e-a8085e215827","3dcd2c96-72b1-4a9f-b65c-08198d63b7df","461ab478-3cf6-4e9b-ba7d-0331b379cacf","0bf27280-f246-4087-9dd4-3649c57810bb","b6bb039f-5f5e-4aa7-bc70-5fb95935e2b0","cadee441-f07c-4414-8c9b-a3c02a734612","f7b4e985-719a-4547-b624-94612d520991","a36eda9b-0e93-4a71-a06a-9442b6d0e4e1","4a3901a4-194f-4a15-9c85-3d0982afcf31","f7480256-8b32-419a-8983-e2c413040dba","4c6b2aca-d940-42af-a068-418f015d277a","c1adf643-ee59-4251-bbf8-49f54265f833","78c329f9-f0c9-486d-9e54-0123699fb9e1","0dad9bef-cfcc-4216-86c8-9ccd6b8613d8","2f86c490-ea26-4830-b847-cf12580735bc","62a2019f-7410-4251-95ed-181925ade6e4","64c28c73-5a2a-4bb0-bcec-9948463a9c8f","d02f2dcc-b699-4441-a86c-ce386675eb7a","daa3d9d1-c906-41f3-83a2-c47f2283da48","311c05c2-a2b2-4051-b0b9-0427015aa980","5b8a6767-2d46-401c-9f85-d427dda9eff7","a53c3ef3-d89d-4c63-b3cd-521d1de531c5","d4371159-b58a-40a4-8060-d345843b5468","96b3e35a-e174-49cd-8695-acd7d23e7710","e492d645-7d2e-4f8a-a43a-9999456e9f72","2ceee427-50d3-4bfe-8ccf-9efb11a90fb7","79e1c8f6-59cd-4efa-9efa-0762d4b1a10c","89fed26e-1cad-4c0b-8695-d6f3562ba8d5","8e76c7c7-04fd-47c9-8db9-6f74ceffe144","288371ef-96b6-4ce3-9be1-1d9d309b400c","22a68d3e-0d12-c5c3-11e9-2e70941bde00","2e6f96d0-d928-4775-a7db-3e998fce675b","f93faee5-589b-4508-a56f-bcf0b3927760","22109c02-910d-4bec-bd79-50e391634c38","9dd8b4f9-9db8-4a16-abcd-bf32219e0301","fcb96831-1c51-4003-adc2-3a3c34e45feb","76795d1b-e1f2-4d1d-b42a-f1d4448c63c0"]},{"source":"ClinicalTrials","ids":["NCT00361322","NCT00757523","NCT00807014","NCT00841776","NCT01015638","NCT01016977","NCT01047189","NCT01111994","NCT01422785","NCT01448733","NCT01769235","NCT01788384","NCT01796665","NCT01915732","NCT02005666","NCT03717506","NCT04321070"]}],"maxPhaseForIndication":4},{"disease":"EFO_1001312","efoName":"endometritis","references":[{"source":"DailyMed","ids":["00088ecd-e45d-4080-b124-e66376ad7694"]}],"maxPhaseForIndication":4},{"disease":"EFO_1001362","efoName":"lung abscess","references":[{"source":"DailyMed","ids":["00088ecd-e45d-4080-b124-e66376ad7694"]}],"maxPhaseForIndication":4},{"disease":"EFO_0003106","efoName":"pneumonia","references":[{"source":"DailyMed","ids":["00088ecd-e45d-4080-b124-e66376ad7694"]}],"maxPhaseForIndication":4},{"disease":"EFO_1001240","efoName":"vulvovaginitis","references":[{"source":"ClinicalTrials","ids":["NCT00616330"]}],"maxPhaseForIndication":3},{"disease":"EFO_1001753","efoName":"abdominal abscess","references":[{"source":"DailyMed","ids":["00088ecd-e45d-4080-b124-e66376ad7694"]},{"source":"ClinicalTrials","ids":["NCT03476941"]}],"maxPhaseForIndication":4},{"disease":"EFO_0008588","efoName":"peritonitis","references":[{"source":"DailyMed","ids":["00088ecd-e45d-4080-b124-e66376ad7694"]}],"maxPhaseForIndication":4},{"disease":"EFO_0003932","efoName":"bacterial vaginosis","references":[{"source":"DailyMed","ids":["f9be442d-0782-4b93-828f-9ebbf67dbced","dac31f82-b35e-49b9-aff9-f0101292f1be"]},{"source":"ClinicalTrials","ids":["NCT04370548"]}],"maxPhaseForIndication":4},{"disease":"EFO_0000544","efoName":"infection","references":[{"source":"DailyMed","ids":["00088ecd-e45d-4080-b124-e66376ad7694"]}],"maxPhaseForIndication":4},{"disease":"MONDO_0024355","efoName":"respiratory tract infectious disorder","references":[{"source":"DailyMed","ids":["00088ecd-e45d-4080-b124-e66376ad7694"]}],"maxPhaseForIndication":4},{"disease":"EFO_1001314","efoName":"pseudomembranous enterocolitis","references":[{"source":"DailyMed","ids":["288371ef-96b6-4ce3-9be1-1d9d309b400c","311c05c2-a2b2-4051-b0b9-0427015aa980"]}],"maxPhaseForIndication":4},{"disease":"EFO_1001084","efoName":"parametritis","references":[{"source":"DailyMed","ids":["00088ecd-e45d-4080-b124-e66376ad7694"]}],"maxPhaseForIndication":4},{"disease":"EFO_0003097","efoName":"empyema","references":[{"source":"DailyMed","ids":["00088ecd-e45d-4080-b124-e66376ad7694"]}],"maxPhaseForIndication":4},{"disease":"EFO_0009549","efoName":"female reproductive system disease","references":[{"source":"DailyMed","ids":["00088ecd-e45d-4080-b124-e66376ad7694"]}],"maxPhaseForIndication":4},{"disease":"EFO_0000555","efoName":"irritable bowel syndrome","references":[{"source":"DailyMed","ids":["311c05c2-a2b2-4051-b0b9-0427015aa980"]}],"maxPhaseForIndication":4},{"disease":"HP_0100806","efoName":"sepsis","references":[{"source":"DailyMed","ids":["00088ecd-e45d-4080-b124-e66376ad7694"]}],"maxPhaseForIndication":4},{"disease":"EFO_0003102","efoName":"osteomyelitis","references":[{"source":"DailyMed","ids":["00088ecd-e45d-4080-b124-e66376ad7694"]},{"source":"ClinicalTrials","ids":["NCT02099240"]}],"maxPhaseForIndication":4},{"disease":"EFO_1000760","efoName":"rosacea","references":[{"source":"ClinicalTrials","ids":["NCT00823901"]}],"maxPhaseForIndication":2},{"disease":"EFO_0003030","efoName":"abscess","references":[{"source":"DailyMed","ids":["00088ecd-e45d-4080-b124-e66376ad7694"]}],"maxPhaseForIndication":4}],"approvedIndications":["EFO_0003097","EFO_0000555","EFO_1001362","EFO_1001753","EFO_0003102","EFO_0003894","MONDO_0024355","EFO_0009549","EFO_0003106","HP_0100806","EFO_1001084","EFO_0008588","EFO_0000544","EFO_0003932","EFO_1001314","EFO_0003030","EFO_1001312"],"indicationCount":19}
{"id":"CHEMBL35","indications":[{"disease":"EFO_0009662","efoName":"common wart","references":[{"source":"ClinicalTrials","ids":["NCT02971891"]}],"maxPhaseForIndication":3},{"disease":"EFO_0009373","efoName":"edema","references":[{"source":"ClinicalTrials","ids":["NCT01887379"]}],"maxPhaseForIndication":1},{"disease":"EFO_0004255","efoName":"nephrotic syndrome","references":[{"source":"DailyMed","ids":["abda01bf-7391-40f2-a3d5-04deec6789ab","6040a2ec-3385-44dd-9f8e-f87ad6474be7","c5db4434-0b47-038c-e053-2995a90ad7fe","3a731de9-de4e-b384-ede3-aea16c156e8b","f20176fb-205c-4368-b510-cbd296cb8152","f2dcb470-240b-4919-8b12-aa1f6faacd49","bc37912e-d5f8-468c-bb55-f2328649dfc7","1d2a8ab4-48a1-47f9-8ac8-d04b100fcbd8","79d9aef8-cfb9-4f6e-ac15-f830d7ea2324","0ce6239f-f2b3-44cc-abd6-9d0a304ef0d4","1b9117d5-0dd9-4577-a1fd-bb0aaf7e68ec","f3369d36-68a4-4737-91fa-34de6ab9ad94","1d95a4e7-6db4-4e90-b240-d08203733664","a6fce940-8009-4f80-99dc-a67be052d45a","9d9475f1-1ab5-4187-b784-943dad2f6dea","bf2513c1-49f5-4f6a-a76d-1c6a9e6c5dfb","7abe8819-6aab-4b1c-841e-bd2830d49faf","2633c775-8a3e-44d4-8909-0f34dc59d405","d71487aa-c181-4549-a16a-61551490dec0","8610f683-1459-479f-9ced-5c766e134542","b75e6570-c96a-4362-b1e6-2690b859816a","a9bc9926-229c-4563-803c-df8f9e13717b","0c50f82b-e9f0-4aab-b47e-b1113aa3862f","af062839-6f6d-4949-9ddb-76dba7cee92c","d680e40c-5126-46dc-a44d-8ff95e66e920","2b0cbe8e-f1c0-4883-94ff-ad603af20655","2c9b4d8f-0770-482d-a9e6-9c616a440b1a","4576e871-14c2-4d9e-b0be-2f0054b92514","012141a6-7c5d-4598-91ed-3960ed0c57d7","4b635500-474a-4944-a66a-b305443344ae","39fd32f2-6bb7-4a65-d298-e48d26bc80c7","513a6195-7dc6-4fd3-8de6-2b8aa069d90c","6cd695c7-13d6-4444-9db5-2b8c8e163376","b609768a-43a0-4cb9-8eca-b42e217ecd3b","a5c17058-c920-4d20-97c8-89b8b712cbce","71b48f4d-9936-448c-9e3a-33f1182e1039","3a2efcd1-9490-4113-974d-21da8ebd7e03","682d3324-7989-4784-9b1d-9f9257f00fec","8e0bac29-5a8b-4d4e-93b3-2e21eb3b0650","d30e72ae-dff7-065d-3aff-d70758bc8590","bcd8df1e-1145-47a2-ae17-4a8759e89fa6","6c252efd-080a-46dd-9c50-e1d3ed126c8d","342a0b3b-3638-4c43-9ff6-1f8cfd6c5b6c","708b157c-845d-4776-9ced-6ae4aae10210","869c9eeb-baae-4189-aa5e-0b4e1ee172d2","2f5bc0c3-b2a8-4426-b648-799c0d0648ba","d562faea-2800-4ed6-9213-88f072e21134","50c48b11-8a70-435e-9028-4748bd82593f","11f60f1a-42a4-426a-98b3-7e6cfbee3407","9ec7808e-9201-4b8c-9790-d329320dc6c4"]}],"maxPhaseForIndication":4},{"disease":"EFO_1001134","efoName":"pulmonary edema","references":[{"source":"DailyMed","ids":["c5db4434-0b47-038c-e053-2995a90ad7fe"]}],"maxPhaseForIndication":4},{"disease":"EFO_0002496","efoName":"actinic keratosis","references":[{"source":"ClinicalTrials","ids":["NCT03684772"]}],"maxPhaseForIndication":2},{"disease":"EFO_0003884","efoName":"chronic kidney disease","references":[{"source":"ClinicalTrials","ids":["NCT04622709"]}],"maxPhaseForIndication":2},{"disease":"MONDO_0005148","efoName":"type 2 diabetes mellitus","references":[{"source":"ClinicalTrials","ids":["NCT00000620","NCT00671424"]}],"maxPhaseForIndication":3},{"disease":"Orphanet_70589","efoName":"bronchopulmonary dysplasia","references":[{"source":"ClinicalTrials","ids":["NCT02527798"]}],"maxPhaseForIndication":2},{"disease":"EFO_0003144","efoName":"heart failure","references":[{"source":"ClinicalTrials","ids":["NCT00372762","NCT00577135","NCT00953303","NCT01125514","NCT02329834","NCT02350725","NCT02689180","NCT02721511","NCT02877095","NCT03296813","NCT03837470","NCT03901729","NCT04384653","NCT04533997","NCT04628325"]}],"maxPhaseForIndication":4},{"disease":"EFO_0001645","efoName":"coronary artery disease","references":[{"source":"ClinicalTrials","ids":["NCT00000620"]}],"maxPhaseForIndication":3},{"disease":"EFO_0004610","efoName":"acute lung injury","references":[{"source":"ClinicalTrials","ids":["NCT00624650"]}],"maxPhaseForIndication":2},{"disease":"EFO_0000668","efoName":"preeclampsia","references":[{"source":"ClinicalTrials","ids":["NCT04752475"]}],"maxPhaseForIndication":3},{"disease":"MONDO_0024664","efoName":"hypertension, pregnancy-induced","references":[{"source":"ClinicalTrials","ids":["NCT03556761"]}],"maxPhaseForIndication":2},{"disease":"EFO_0000319","efoName":"cardiovascular disease","references":[{"source":"ATC","ids":["C03CA01"]}],"maxPhaseForIndication":4},{"disease":"EFO_1000391","efoName":"nasal cavity polyp","references":[{"source":"ClinicalTrials","ids":["NCT03362515"]}],"maxPhaseForIndication":2},{"disease":"EFO_0000565","efoName":"leukemia","references":[{"source":"ClinicalTrials","ids":["NCT01756677"]}],"maxPhaseForIndication":1},{"disease":"EFO_0003086","efoName":"kidney disease","references":[{"source":"ClinicalTrials","ids":["NCT00151827","NCT00702728","NCT00936923"]}],"maxPhaseForIndication":3},{"disease":"EFO_1002048","efoName":"kidney failure","references":[{"source":"ClinicalTrials","ids":["NCT00298454","NCT01724788"]}],"maxPhaseForIndication":3},{"disease":"EFO_0000311","efoName":"cancer","references":[{"source":"ClinicalTrials","ids":["NCT02501213"]}],"maxPhaseForIndication":2},{"disease":"EFO_0008583","efoName":"acute myocardial infarction","references":[{"source":"ClinicalTrials","ids":["NCT02905760"]}],"maxPhaseForIndication":3},{"disease":"EFO_0003914","efoName":"atherosclerosis","references":[{"source":"ClinicalTrials","ids":["NCT00000620"]}],"maxPhaseForIndication":3},{"disease":"EFO_0003827","efoName":"pulmonary embolism","references":[{"source":"ClinicalTrials","ids":["NCT02268903"]}],"maxPhaseForIndication":3},{"disease":"MONDO_0001134","efoName":"essential hypertension","references":[{"source":"ClinicalTrials","ids":["NCT00151827"]}],"maxPhaseForIndication":3},{"disease":"EFO_0003917","efoName":"premature birth","references":[{"source":"ClinicalTrials","ids":["NCT03946891"]}],"maxPhaseForIndication":0},{"disease":"MONDO_0005090","efoName":"schizophrenia","references":[{"source":"ClinicalTrials","ids":["NCT00611741"]}],"maxPhaseForIndication":1},{"disease":"EFO_0003818","efoName":"lung disease","references":[{"source":"ClinicalTrials","ids":["NCT00618852"]}],"maxPhaseForIndication":3},{"disease":"EFO_0000373","efoName":"congestive heart failure","references":[{"source":"DailyMed","ids":["abda01bf-7391-40f2-a3d5-04deec6789ab","6040a2ec-3385-44dd-9f8e-f87ad6474be7","c5db4434-0b47-038c-e053-2995a90ad7fe","3a731de9-de4e-b384-ede3-aea16c156e8b","f20176fb-205c-4368-b510-cbd296cb8152","f2dcb470-240b-4919-8b12-aa1f6faacd49","bc37912e-d5f8-468c-bb55-f2328649dfc7","1d2a8ab4-48a1-47f9-8ac8-d04b100fcbd8","79d9aef8-cfb9-4f6e-ac15-f830d7ea2324","0ce6239f-f2b3-44cc-abd6-9d0a304ef0d4","1b9117d5-0dd9-4577-a1fd-bb0aaf7e68ec","f3369d36-68a4-4737-91fa-34de6ab9ad94","1d95a4e7-6db4-4e90-b240-d08203733664","a6fce940-8009-4f80-99dc-a67be052d45a","9d9475f1-1ab5-4187-b784-943dad2f6dea","bf2513c1-49f5-4f6a-a76d-1c6a9e6c5dfb","7abe8819-6aab-4b1c-841e-bd2830d49faf","2633c775-8a3e-44d4-8909-0f34dc59d405","d71487aa-c181-4549-a16a-61551490dec0","8610f683-1459-479f-9ced-5c766e134542","b75e6570-c96a-4362-b1e6-2690b859816a","a9bc9926-229c-4563-803c-df8f9e13717b","0c50f82b-e9f0-4aab-b47e-b1113aa3862f","af062839-6f6d-4949-9ddb-76dba7cee92c","d680e40c-5126-46dc-a44d-8ff95e66e920","2b0cbe8e-f1c0-4883-94ff-ad603af20655","2c9b4d8f-0770-482d-a9e6-9c616a440b1a","4576e871-14c2-4d9e-b0be-2f0054b92514","fc626d03-a44c-4a9b-b87c-d57450d45e35","012141a6-7c5d-4598-91ed-3960ed0c57d7","4b635500-474a-4944-a66a-b305443344ae","39fd32f2-6bb7-4a65-d298-e48d26bc80c7","513a6195-7dc6-4fd3-8de6-2b8aa069d90c","6cd695c7-13d6-4444-9db5-2b8c8e163376","b609768a-43a0-4cb9-8eca-b42e217ecd3b","a5c17058-c920-4d20-97c8-89b8b712cbce","71b48f4d-9936-448c-9e3a-33f1182e1039","3a2efcd1-9490-4113-974d-21da8ebd7e03","682d3324-7989-4784-9b1d-9f9257f00fec","8e0bac29-5a8b-4d4e-93b3-2e21eb3b0650","d30e72ae-dff7-065d-3aff-d70758bc8590","bcd8df1e-1145-47a2-ae17-4a8759e89fa6","6c252efd-080a-46dd-9c50-e1d3ed126c8d","342a0b3b-3638-4c43-9ff6-1f8cfd6c5b6c","708b157c-845d-4776-9ced-6ae4aae10210","869c9eeb-baae-4189-aa5e-0b4e1ee172d2","2f5bc0c3-b2a8-4426-b648-799c0d0648ba","d562faea-2800-4ed6-9213-88f072e21134","50c48b11-8a70-435e-9028-4748bd82593f","11f60f1a-42a4-426a-98b3-7e6cfbee3407","9ec7808e-9201-4b8c-9790-d329320dc6c4"]},{"source":"ClinicalTrials","ids":["NCT00355667","NCT00409942","NCT00652652","NCT02579057","NCT03730961"]}],"maxPhaseForIndication":4},{"disease":"EFO_0001422","efoName":"cirrhosis of liver","references":[{"source":"ClinicalTrials","ids":["NCT04216784"]},{"source":"DailyMed","ids":["9ec7808e-9201-4b8c-9790-d329320dc6c4","39fd32f2-6bb7-4a65-d298-e48d26bc80c7","c5db4434-0b47-038c-e053-2995a90ad7fe","f2dcb470-240b-4919-8b12-aa1f6faacd49","bc37912e-d5f8-468c-bb55-f2328649dfc7","1d2a8ab4-48a1-47f9-8ac8-d04b100fcbd8","6cd695c7-13d6-4444-9db5-2b8c8e163376","79d9aef8-cfb9-4f6e-ac15-f830d7ea2324","1b9117d5-0dd9-4577-a1fd-bb0aaf7e68ec","71b48f4d-9936-448c-9e3a-33f1182e1039","3a2efcd1-9490-4113-974d-21da8ebd7e03","682d3324-7989-4784-9b1d-9f9257f00fec","a6fce940-8009-4f80-99dc-a67be052d45a","8e0bac29-5a8b-4d4e-93b3-2e21eb3b0650","8610f683-1459-479f-9ced-5c766e134542","a9bc9926-229c-4563-803c-df8f9e13717b","d30e72ae-dff7-065d-3aff-d70758bc8590","d680e40c-5126-46dc-a44d-8ff95e66e920","6c252efd-080a-46dd-9c50-e1d3ed126c8d","2b0cbe8e-f1c0-4883-94ff-ad603af20655","342a0b3b-3638-4c43-9ff6-1f8cfd6c5b6c","2c9b4d8f-0770-482d-a9e6-9c616a440b1a","708b157c-845d-4776-9ced-6ae4aae10210","869c9eeb-baae-4189-aa5e-0b4e1ee172d2","d562faea-2800-4ed6-9213-88f072e21134","11f60f1a-42a4-426a-98b3-7e6cfbee3407","4b635500-474a-4944-a66a-b305443344ae"]}],"maxPhaseForIndication":4},{"disease":"EFO_0000400","efoName":"diabetes mellitus","references":[{"source":"ClinicalTrials","ids":["NCT03010475"]}],"maxPhaseForIndication":1},{"disease":"HP_0011950","efoName":"bronchiolitis","references":[{"source":"ClinicalTrials","ids":["NCT00261937","NCT00512811","NCT02469597"]}],"maxPhaseForIndication":3},{"disease":"HP_0001919","efoName":"acute kidney injury","references":[{"source":"ClinicalTrials","ids":["NCT00978354","NCT02983422"]}],"maxPhaseForIndication":2},{"disease":"HP_0002094","efoName":"dyspnea","references":[{"source":"ClinicalTrials","ids":["NCT01440764","NCT02524054","NCT02881866"]}],"maxPhaseForIndication":1},{"disease":"HP_0003124","efoName":"hypercholesterolemia","references":[{"source":"ClinicalTrials","ids":["NCT00000620"]}],"maxPhaseForIndication":3},{"disease":"EFO_0000222","efoName":"acute myeloid leukemia","references":[{"source":"ClinicalTrials","ids":["NCT02575963"]}],"maxPhaseForIndication":1},{"disease":"EFO_0009840","efoName":"tachypnea","references":[{"source":"ClinicalTrials","ids":["NCT03208894"]}],"maxPhaseForIndication":3},{"disease":"EFO_0000537","efoName":"hypertension","references":[{"source":"ClinicalTrials","ids":["NCT00000620","NCT00421863","NCT02450773","NCT02832973"]},{"source":"DailyMed","ids":["abda01bf-7391-40f2-a3d5-04deec6789ab","13d83c0c-6328-4d64-99c1-5a68b132fed9","19926550-0376-42b1-bf67-56871e5bd7a3","3a731de9-de4e-b384-ede3-aea16c156e8b","f20176fb-205c-4368-b510-cbd296cb8152","f2dcb470-240b-4919-8b12-aa1f6faacd49","bc37912e-d5f8-468c-bb55-f2328649dfc7","1d2a8ab4-48a1-47f9-8ac8-d04b100fcbd8","79d9aef8-cfb9-4f6e-ac15-f830d7ea2324","0ce6239f-f2b3-44cc-abd6-9d0a304ef0d4","f3369d36-68a4-4737-91fa-34de6ab9ad94","1d95a4e7-6db4-4e90-b240-d08203733664","a6fce940-8009-4f80-99dc-a67be052d45a","9d9475f1-1ab5-4187-b784-943dad2f6dea","7abe8819-6aab-4b1c-841e-bd2830d49faf","b75e6570-c96a-4362-b1e6-2690b859816a","af062839-6f6d-4949-9ddb-76dba7cee92c","0c50f82b-e9f0-4aab-b47e-b1113aa3862f","d680e40c-5126-46dc-a44d-8ff95e66e920","2b0cbe8e-f1c0-4883-94ff-ad603af20655","8611f3c2-b182-4aca-a0a6-ad40d13a34e0","4576e871-14c2-4d9e-b0be-2f0054b92514","fc626d03-a44c-4a9b-b87c-d57450d45e35","012141a6-7c5d-4598-91ed-3960ed0c57d7","4b635500-474a-4944-a66a-b305443344ae","557fee5e-166c-4f0f-bb4d-37c6ce3496ad","529fe6c0-c1ef-4fe1-bb8e-cf748e3a3a85","11d45137-e4cf-4791-ad37-05e1247ddeef","513a6195-7dc6-4fd3-8de6-2b8aa069d90c","6cd695c7-13d6-4444-9db5-2b8c8e163376","b609768a-43a0-4cb9-8eca-b42e217ecd3b","cfe67179-fbfe-402d-9326-07373bd93951","a5c17058-c920-4d20-97c8-89b8b712cbce","3a2efcd1-9490-4113-974d-21da8ebd7e03","682d3324-7989-4784-9b1d-9f9257f00fec","ea5805d3-400b-4978-b27d-bd2b5b1cb636","d30e72ae-dff7-065d-3aff-d70758bc8590","bcd8df1e-1145-47a2-ae17-4a8759e89fa6","6c252efd-080a-46dd-9c50-e1d3ed126c8d","b64c46ee-621e-4dd9-8458-beaa654a7c19","708b157c-845d-4776-9ced-6ae4aae10210","2f5bc0c3-b2a8-4426-b648-799c0d0648ba","d562faea-2800-4ed6-9213-88f072e21134","50c48b11-8a70-435e-9028-4748bd82593f","11f60f1a-42a4-426a-98b3-7e6cfbee3407","9ec7808e-9201-4b8c-9790-d329320dc6c4"]}],"maxPhaseForIndication":4}],"approvedIndications":["EFO_0001422","EFO_0003144","EFO_1001134","EFO_0004255","EFO_0000373","EFO_0000319","EFO_0000537"],"indicationCount":36}
{"id":"CHEMBL4297838","indications":[{"disease":"EFO_0000756","efoName":"melanoma","references":[{"source":"ClinicalTrials","ids":["NCT04126876"]}],"maxPhaseForIndication":2},{"disease":"EFO_0000311","efoName":"cancer","references":[{"source":"ClinicalTrials","ids":["NCT04196283","NCT04270864"]}],"maxPhaseForIndication":2},{"disease":"EFO_0000616","efoName":"neoplasm","references":[{"source":"ClinicalTrials","ids":["NCT03865082"]}],"maxPhaseForIndication":2}],"approvedIndications":[],"indicationCount":3}
{"id":"CHEMBL1201533","indications":[{"disease":"EFO_1001062","efoName":"nodular goiter","references":[{"source":"ClinicalTrials","ids":["NCT00275171"]}],"maxPhaseForIndication":2},{"disease":"EFO_0002892","efoName":"thyroid carcinoma","references":[{"source":"DailyMed","ids":["b52dfa36-f90b-4e19-9b5e-26db9d04df2b"]}],"maxPhaseForIndication":4},{"disease":"EFO_0003841","efoName":"thyroid neoplasm","references":[{"source":"ClinicalTrials","ids":["NCT00196729"]}],"maxPhaseForIndication":4},{"disease":"EFO_0004237","efoName":"graves disease","references":[{"source":"ClinicalTrials","ids":["NCT00145366"]}],"maxPhaseForIndication":2},{"disease":"MONDO_0002108","efoName":"thyroid cancer","references":[{"source":"ClinicalTrials","ids":["NCT00295763","NCT00435851","NCT01837745","NCT03244956","NCT03841617","NCT04137185","NCT04447183","NCT04964284","NCT04971473"]}],"maxPhaseForIndication":4}],"approvedIndications":["EFO_0003841","EFO_0002892","MONDO_0002108"],"indicationCount":5}
{"id":"CHEMBL2107857","indications":[{"disease":"EFO_0010269","efoName":"amenorrhea","references":[{"source":"ClinicalTrials","ids":["NCT00130117"]}],"maxPhaseForIndication":2},{"disease":"EFO_0000195","efoName":"metabolic syndrome","references":[{"source":"ClinicalTrials","ids":["NCT00140244"]}],"maxPhaseForIndication":2},{"disease":"EFO_1001348","efoName":"hiv-associated lipodystrophy syndrome","references":[{"source":"ClinicalTrials","ids":["NCT00362440"]}],"maxPhaseForIndication":2},{"disease":"Orphanet_98306","efoName":"familial partial lipodystrophy","references":[{"source":"ClinicalTrials","ids":["NCT02404896"]}],"maxPhaseForIndication":2},{"disease":"EFO_0003095","efoName":"non-alcoholic fatty liver disease","references":[{"source":"ClinicalTrials","ids":["NCT00596934"]}],"maxPhaseForIndication":2},{"disease":"EFO_0001421","efoName":"liver disease","references":[{"source":"DailyMed","ids":["c986f93b-855d-4ef0-b620-5d41a0513e48"]}],"maxPhaseForIndication":4},{"disease":"MONDO_0005147","efoName":"type 1 diabetes mellitus","references":[{"source":"ClinicalTrials","ids":["NCT01268644"]}],"maxPhaseForIndication":1},{"disease":"EFO_0002614","efoName":"insulin resistance","references":[{"source":"ClinicalTrials","ids":["NCT00027456"]}],"maxPhaseForIndication":2},{"disease":"EFO_1000727","efoName":"lipodystrophy","references":[{"source":"FDA","ids":["label/2014/125390s000lbl.pdf"]},{"source":"ClinicalTrials","ids":["NCT00005905","NCT00025883","NCT01778556"]}],"maxPhaseForIndication":4},{"disease":"EFO_0001073","efoName":"obesity","references":[{"source":"ClinicalTrials","ids":["NCT00050791","NCT00073242","NCT00392925","NCT00673387","NCT00710814","NCT00819234","NCT01155180","NCT01235741","NCT01275053"]}],"maxPhaseForIndication":3}],"approvedIndications":["EFO_0001421","EFO_1000727"],"indicationCount":10}
{"id":"CHEMBL4582651","indications":[{"disease":"EFO_0003060","efoName":"non-small cell lung carcinoma","references":[{"source":"ClinicalTrials","ids":["NCT04302025"]},{"source":"FDA","ids":["label/2020/213721s000lbl.pdf"]}],"maxPhaseForIndication":4},{"disease":"MONDO_0002108","efoName":"thyroid cancer","references":[{"source":"ClinicalTrials","ids":["NCT04760288"]}],"maxPhaseForIndication":3},{"disease":"MONDO_0015277","efoName":"medullary thyroid gland carcinoma","references":[{"source":"DailyMed","ids":["beb226ab-f684-42de-93a4-edb2263ddb11"]}],"maxPhaseForIndication":4},{"disease":"EFO_0000616","efoName":"neoplasm","references":[{"source":"ClinicalTrials","ids":["NCT04589845"]}],"maxPhaseForIndication":2}],"approvedIndications":["MONDO_0015277","EFO_0003060"],"indicationCount":4}
{"id":"CHEMBL3702854","indications":[{"disease":"EFO_0007160","efoName":"autoimmune thrombocytopenic purpura","references":[{"source":"ClinicalTrials","ids":["NCT03395210","NCT04562766"]}],"maxPhaseForIndication":3},{"disease":"EFO_1000749","efoName":"pemphigus","references":[{"source":"ClinicalTrials","ids":["NCT03762265"]}],"maxPhaseForIndication":3},{"disease":"EFO_0004719","efoName":"pemphigus vulgaris","references":[{"source":"ClinicalTrials","ids":["NCT02704429"]}],"maxPhaseForIndication":3},{"disease":"MONDO_0017287","efoName":"igg4-related disease","references":[{"source":"ClinicalTrials","ids":["NCT04520451"]}],"maxPhaseForIndication":2}],"approvedIndications":[],"indicationCount":4}
{"id":"CHEMBL3833413","indications":[{"disease":"HP_0002829","efoName":"arthralgia","references":[{"source":"ATC","ids":["M02AA03"]}],"maxPhaseForIndication":0},{"disease":"EFO_0005755","efoName":"rheumatic disease","references":[{"source":"ATC","ids":["M01AA05"]}],"maxPhaseForIndication":0},{"disease":"HP_0003326","efoName":"myalgia","references":[{"source":"ATC","ids":["M02AA03"]}],"maxPhaseForIndication":0}],"approvedIndications":[],"indicationCount":3}
{"id":"CHEMBL488","indications":[{"disease":"EFO_0000616","efoName":"neoplasm","references":[{"source":"ATC","ids":["L02BG01"]}],"maxPhaseForIndication":4},{"disease":"MONDO_0007254","efoName":"breast cancer","references":[{"source":"ClinicalTrials","ids":["NCT00309491"]}],"maxPhaseForIndication":3},{"disease":"MONDO_0008315","efoName":"prostate cancer","references":[{"source":"ClinicalTrials","ids":["NCT00006371"]}],"maxPhaseForIndication":2}],"approvedIndications":["EFO_0000616"],"indicationCount":3}
{"id":"CHEMBL2109463","indications":[{"disease":"MONDO_0004979","efoName":"asthma","references":[{"source":"ClinicalTrials","ids":["NCT00411814","NCT00843193"]}],"maxPhaseForIndication":2}],"approvedIndications":[],"indicationCount":1}
{"id":"CHEMBL2103807","indications":[{"disease":"EFO_0001668","efoName":"human papilloma virus infection","references":[{"source":"ClinicalTrials","ids":["NCT00117884","NCT00312286"]}],"maxPhaseForIndication":2}],"approvedIndications":[],"indicationCount":1}
{"id":"CHEMBL4297646","indications":[{"disease":"EFO_0005252","efoName":"orthostatic hypotension","references":[{"source":"ClinicalTrials","ids":["NCT03750552","NCT03829657","NCT04095793","NCT04688632"]}],"maxPhaseForIndication":3},{"disease":"EFO_0005687","efoName":"fibromyalgia","references":[{"source":"ClinicalTrials","ids":["NCT01693692"]}],"maxPhaseForIndication":2},{"disease":"EFO_0003888","efoName":"attention deficit hyperactivity disorder","references":[{"source":"ClinicalTrials","ids":["NCT01458340"]}],"maxPhaseForIndication":2}],"approvedIndications":[],"indicationCount":3}
{"id":"CHEMBL190083","indications":[{"disease":"MONDO_0008315","efoName":"prostate cancer","references":[{"source":"ClinicalTrials","ids":["NCT00045123"]}],"maxPhaseForIndication":2},{"disease":"HP_0000726","efoName":"dementia","references":[{"source":"ClinicalTrials","ids":["NCT00105547","NCT00322036"]}],"maxPhaseForIndication":3},{"disease":"MONDO_0004975","efoName":"alzheimer disease","references":[{"source":"ClinicalTrials","ids":["NCT00105547","NCT00322036","NCT00380276"]}],"maxPhaseForIndication":3}],"approvedIndications":[],"indicationCount":3}
{"id":"CHEMBL2108597","indications":[{"disease":"EFO_0000341","efoName":"chronic obstructive pulmonary disease","references":[{"source":"ClinicalTrials","ids":["NCT03050424"]}],"maxPhaseForIndication":2},{"disease":"EFO_0004270","efoName":"restless legs syndrome","references":[{"source":"ClinicalTrials","ids":["NCT00685815","NCT01382901","NCT02397057"]}],"maxPhaseForIndication":3},{"disease":"HP_0001891","efoName":"iron deficiency anemia","references":[{"source":"ClinicalTrials","ids":["NCT00982007","NCT01100879","NCT01101399","NCT01245777","NCT01290315","NCT01307007","NCT01950247","NCT02410213","NCT02541708","NCT03237065","NCT03238911","NCT03399084","NCT03523117","NCT03591406","NCT03759964","NCT03817957","NCT04087993","NCT04269707","NCT04320966","NCT04976179"]},{"source":"DailyMed","ids":["517b4a19-45b3-4286-9f6a-ced4e10447de"]}],"maxPhaseForIndication":4},{"disease":"EFO_0004540","efoName":"chronic fatigue syndrome","references":[{"source":"ClinicalTrials","ids":["NCT02517151"]}],"maxPhaseForIndication":2},{"disease":"MONDO_0002280","efoName":"anemia","references":[{"source":"DailyMed","ids":["517b4a19-45b3-4286-9f6a-ced4e10447de"]}],"maxPhaseForIndication":4},{"disease":"EFO_0003144","efoName":"heart failure","references":[{"source":"ClinicalTrials","ids":["NCT02737995","NCT03037931","NCT03074591"]}],"maxPhaseForIndication":3},{"disease":"EFO_0004272","efoName":"anemia (phenotype)","references":[{"source":"ClinicalTrials","ids":["NCT00317226","NCT00317239","NCT00354484","NCT00395993","NCT00396292","NCT00548691","NCT00548860","NCT00703937","NCT00704028","NCT00704353","NCT00740246","NCT01692418","NCT02628860","NCT04968379"]}],"maxPhaseForIndication":4},{"disease":"EFO_0003964","efoName":"hip fracture","references":[{"source":"ClinicalTrials","ids":["NCT01154491"]}],"maxPhaseForIndication":3},{"disease":"EFO_1000984","efoName":"inflammatory breast carcinoma","references":[{"source":"ClinicalTrials","ids":["NCT02125344"]}],"maxPhaseForIndication":3},{"disease":"MONDO_0021148","efoName":"female reproductive system neoplasm","references":[{"source":"ClinicalTrials","ids":["NCT04625530"]}],"maxPhaseForIndication":3}],"approvedIndications":["MONDO_0002280","EFO_0004272","HP_0001891"],"indicationCount":10}
{"id":"CHEMBL3183075","indications":[{"disease":"EFO_0003948","efoName":"gastroesophageal reflux disease","references":[{"source":"ClinicalTrials","ids":["NCT00373334"]},{"source":"ATC","ids":["A02BA04"]}],"maxPhaseForIndication":4},{"disease":"HP_0004398","efoName":"peptic ulcer","references":[{"source":"ATC","ids":["A02BA04"]}],"maxPhaseForIndication":4},{"disease":"HP_0100633","efoName":"esophagitis","references":[{"source":"DailyMed","ids":["005909e4-77d2-440f-a10b-30fab27ffbc3"]}],"maxPhaseForIndication":4},{"disease":"EFO_1000948","efoName":"gastroparesis","references":[{"source":"ClinicalTrials","ids":["NCT02232308"]}],"maxPhaseForIndication":1},{"disease":"EFO_0000217","efoName":"gastritis","references":[{"source":"ClinicalTrials","ids":["NCT03509831"]}],"maxPhaseForIndication":1},{"disease":"EFO_0004607","efoName":"duodenal ulcer","references":[{"source":"DailyMed","ids":["005909e4-77d2-440f-a10b-30fab27ffbc3"]}],"maxPhaseForIndication":4}],"approvedIndications":["EFO_0003948","HP_0004398","EFO_0004607","HP_0100633"],"indicationCount":6}
{"id":"CHEMBL1201584","indications":[{"disease":"EFO_0008583","efoName":"acute myocardial infarction","references":[{"source":"ClinicalTrials","ids":["NCT00894023","NCT03087539"]}],"maxPhaseForIndication":3},{"disease":"EFO_0008585","efoName":"st elevation myocardial infarction","references":[{"source":"ClinicalTrials","ids":["NCT00712101"]}],"maxPhaseForIndication":3},{"disease":"MONDO_0005299","efoName":"brain ischemia","references":[{"source":"ClinicalTrials","ids":["NCT00073372"]}],"maxPhaseForIndication":3},{"disease":"EFO_0003913","efoName":"angina pectoris","references":[{"source":"ClinicalTrials","ids":["NCT01103440"]}],"maxPhaseForIndication":2},{"disease":"EFO_0000612","efoName":"myocardial infarction","references":[{"source":"ClinicalTrials","ids":["NCT00046228","NCT00299377","NCT00426751","NCT00638638","NCT02181985"]}],"maxPhaseForIndication":3},{"disease":"EFO_0000712","efoName":"stroke","references":[{"source":"ClinicalTrials","ids":["NCT00039832","NCT00046293","NCT00073372","NCT00126139","NCT00167765"]}],"maxPhaseForIndication":3},{"disease":"EFO_1000985","efoName":"intermediate coronary syndrome","references":[{"source":"DailyMed","ids":["033d4c3b-4630-4256-b8f7-9ed5f15de9a3"]},{"source":"ClinicalTrials","ids":["NCT00133003","NCT00269893","NCT00269906"]}],"maxPhaseForIndication":4},{"disease":"HP_0004419","efoName":"recurrent thrombophlebitis","references":[{"source":"ATC","ids":["B01AC13"]}],"maxPhaseForIndication":4},{"disease":"EFO_0002615","efoName":"internal carotid artery stenosis","references":[{"source":"ClinicalTrials","ids":["NCT00178451"]}],"maxPhaseForIndication":1}],"approvedIndications":["EFO_1000985","HP_0004419"],"indicationCount":9}
{"id":"CHEMBL4297308","indications":[{"disease":"EFO_0000198","efoName":"myelodysplastic syndrome","references":[{"source":"ClinicalTrials","ids":["NCT03059615"]}],"maxPhaseForIndication":2},{"disease":"EFO_0000311","efoName":"cancer","references":[{"source":"ClinicalTrials","ids":["NCT01690741"]}],"maxPhaseForIndication":1},{"disease":"EFO_0000222","efoName":"acute myeloid leukemia","references":[{"source":"ClinicalTrials","ids":["NCT03059615"]}],"maxPhaseForIndication":2}],"approvedIndications":[],"indicationCount":3}
{"id":"CHEMBL2109151","indications":[{"disease":"EFO_0000565","efoName":"leukemia","references":[{"source":"ClinicalTrials","ids":["NCT00058396"]}],"maxPhaseForIndication":1},{"disease":"EFO_0000574","efoName":"lymphoma","references":[{"source":"ClinicalTrials","ids":["NCT00058396"]}],"maxPhaseForIndication":1},{"disease":"EFO_0000095","efoName":"chronic lymphocytic leukemia","references":[{"source":"ClinicalTrials","ids":["NCT00046488","NCT00103558","NCT00391066","NCT00801060"]}],"maxPhaseForIndication":2}],"approvedIndications":[],"indicationCount":3}
{"id":"CHEMBL3544988","indications":[{"disease":"EFO_0000546","efoName":"injury","references":[{"source":"ClinicalTrials","ids":["NCT01831804"]}],"maxPhaseForIndication":1},{"disease":"EFO_0003875","efoName":"peripheral vascular disease","references":[{"source":"ClinicalTrials","ids":["NCT02135848"]}],"maxPhaseForIndication":2},{"disease":"EFO_0004272","efoName":"anemia (phenotype)","references":[{"source":"ClinicalTrials","ids":["NCT01376232","NCT01406340","NCT01587898","NCT01587924","NCT01673555","NCT01977482","NCT01977573","NCT02019719","NCT02075463","NCT02243306","NCT02293148","NCT02371603","NCT02689206","NCT02791763","NCT02829320","NCT02876835","NCT02879305","NCT02969655","NCT03029208","NCT03029247","NCT03223337","NCT03239522","NCT03400033","NCT03409107","NCT03446612","NCT03457701","NCT03493386","NCT04640311"]}],"maxPhaseForIndication":3}],"approvedIndications":[],"indicationCount":3}
{"id":"CHEMBL1190199","indications":[{"disease":"MONDO_0004567","efoName":"ileus","references":[{"source":"ClinicalTrials","ids":["NCT00443040"]}],"maxPhaseForIndication":2},{"disease":"EFO_0000555","efoName":"irritable bowel syndrome","references":[{"source":"ClinicalTrials","ids":["NCT00454688","NCT00955994","NCT01100684"]}],"maxPhaseForIndication":3}],"approvedIndications":[],"indicationCount":2}
{"id":"CHEMBL296913","indications":[{"disease":"EFO_0003843","efoName":"pain","references":[{"source":"ClinicalTrials","ids":["NCT00636064"]}],"maxPhaseForIndication":3},{"disease":"MONDO_0005178","efoName":"osteoarthritis","references":[{"source":"ClinicalTrials","ids":["NCT01311804"]}],"maxPhaseForIndication":3}],"approvedIndications":[],"indicationCount":2}
{"id":"CHEMBL3298910","indications":[{"disease":"Orphanet_3389","efoName":"tuberculosis","references":[{"source":"ClinicalTrials","ids":["NCT03563599"]}],"maxPhaseForIndication":2},{"disease":"MONDO_0100096","efoName":"covid-19","references":[{"source":"ClinicalTrials","ids":["NCT04847583"]}],"maxPhaseForIndication":2}],"approvedIndications":[],"indicationCount":2}
{"id":"CHEMBL2107991","indications":[{"disease":"MP_0001914","efoName":"hemorrhage","references":[{"source":"ATC","ids":["B02BC01"]}],"maxPhaseForIndication":4}],"approvedIndications":["MP_0001914"],"indicationCount":1}
{"id":"CHEMBL3545386","indications":[{"disease":"MONDO_0005178","efoName":"osteoarthritis","references":[{"source":"ClinicalTrials","ids":["NCT01207973"]}],"maxPhaseForIndication":1}],"approvedIndications":[],"indicationCount":1}
{"id":"CHEMBL3121849","indications":[{"disease":"EFO_0003047","efoName":"hepatitis c virus infection","references":[{"source":"ClinicalTrials","ids":["NCT02961426","NCT03288636","NCT03362814","NCT04885855"]}],"maxPhaseForIndication":2},{"disease":"EFO_0004220","efoName":"chronic hepatitis c virus infection","references":[{"source":"ClinicalTrials","ids":["NCT03020095","NCT03430830"]}],"maxPhaseForIndication":2},{"disease":"EFO_0004220","efoName":"chronic hepatitis c virus infection","references":[{"source":"ClinicalTrials","ids":["NCT01448200","NCT01859962","NCT02371408"]}],"maxPhaseForIndication":2}],"approvedIndications":[],"indicationCount":3}
{"id":"CHEMBL15797","indications":[{"disease":"EFO_1001475","efoName":"schistosomiasis","references":[{"source":"ClinicalTrials","ids":["NCT01054651"]}],"maxPhaseForIndication":3}],"approvedIndications":[],"indicationCount":1}
{"id":"CHEMBL12089","indications":[{"disease":"EFO_0000400","efoName":"diabetes mellitus","references":[{"source":"ClinicalTrials","ids":["NCT03972215"]}],"maxPhaseForIndication":0},{"disease":"EFO_0000729","efoName":"ulcerative colitis","references":[{"source":"ClinicalTrials","ids":["NCT02365480"]}],"maxPhaseForIndication":1}],"approvedIndications":[],"indicationCount":2}
{"id":"CHEMBL4297976","indications":[{"disease":"Orphanet_79213","efoName":"mucopolysaccharidosis","references":[{"source":"ClinicalTrials","ids":["NCT02350816"]}],"maxPhaseForIndication":2}],"approvedIndications":[],"indicationCount":1}
{"id":"CHEMBL3301572","indications":[{"disease":"EFO_0008525","efoName":"spinal muscular atrophy","references":[{"source":"ClinicalTrials","ids":["NCT01494701","NCT01703988","NCT01780246","NCT01839656","NCT02052791","NCT02193074","NCT02292537","NCT02386553","NCT02462759","NCT02594124","NCT04089566","NCT04729907"]}],"maxPhaseForIndication":3}],"approvedIndications":[],"indicationCount":1}
{"id":"CHEMBL3833375","indications":[{"disease":"EFO_1001888","efoName":"eye infection","references":[{"source":"ATC","ids":["S01AX07"]}],"maxPhaseForIndication":0}],"approvedIndications":[],"indicationCount":1}
{"id":"CHEMBL2140408","indications":[{"disease":"EFO_0000311","efoName":"cancer","references":[{"source":"ClinicalTrials","ids":["NCT00858377"]}],"maxPhaseForIndication":1},{"disease":"MONDO_0004643","efoName":"myeloid leukemia","references":[{"source":"ClinicalTrials","ids":["NCT01380756"]}],"maxPhaseForIndication":1}],"approvedIndications":[],"indicationCount":2}
{"id":"CHEMBL4059888","indications":[{"disease":"EFO_0006318","efoName":"breast ductal adenocarcinoma","references":[{"source":"ClinicalTrials","ids":["NCT03455270"]}],"maxPhaseForIndication":1}],"approvedIndications":[],"indicationCount":1}
{"id":"CHEMBL4594488","indications":[{"disease":"EFO_0004253","efoName":"nephrolithiasis","references":[{"source":"ClinicalTrials","ids":["NCT03924596"]}],"maxPhaseForIndication":1}],"approvedIndications":[],"indicationCount":1}
{"id":"CHEMBL3301595","indications":[{"disease":"EFO_0003888","efoName":"attention deficit hyperactivity disorder","references":[{"source":"ClinicalTrials","ids":["NCT01692782","NCT02160262","NCT02195167","NCT02276209","NCT02428088","NCT02457819","NCT02734693","NCT03231800"]}],"maxPhaseForIndication":3},{"disease":"EFO_0005203","efoName":"eating disorder","references":[{"source":"ClinicalTrials","ids":["NCT02564588","NCT02684279","NCT03107026"]}],"maxPhaseForIndication":3},{"disease":"MONDO_0002009","efoName":"major depressive disorder","references":[{"source":"ClinicalTrials","ids":["NCT00584974"]}],"maxPhaseForIndication":2}],"approvedIndications":[],"indicationCount":3}
{"id":"CHEMBL4297641","indications":[{"disease":"EFO_0000616","efoName":"neoplasm","references":[{"source":"ClinicalTrials","ids":["NCT03895684"]}],"maxPhaseForIndication":1},{"disease":"EFO_0000174","efoName":"ewing sarcoma","references":[{"source":"ClinicalTrials","ids":["NCT03600649"]}],"maxPhaseForIndication":1}],"approvedIndications":[],"indicationCount":2}
{"id":"CHEMBL77101","indications":[{"disease":"HP_0002014","efoName":"diarrhea","references":[{"source":"ClinicalTrials","ids":["NCT00002121"]}],"maxPhaseForIndication":1}],"approvedIndications":[],"indicationCount":1}
{"id":"CHEMBL2059028","indications":[{"disease":"EFO_0000616","efoName":"neoplasm","references":[{"source":"ClinicalTrials","ids":["NCT00004030"]}],"maxPhaseForIndication":1}],"approvedIndications":[],"indicationCount":1}
{"id":"CHEMBL33845","indications":[{"disease":"EFO_1001342","efoName":"helminthiasis","references":[{"source":"ATC","ids":["P02DX02"]}],"maxPhaseForIndication":0}],"approvedIndications":[],"indicationCount":1}
{"id":"CHEMBL1908394","indications":[{"disease":"EFO_0005952","efoName":"non-hodgkins lymphoma","references":[{"source":"ClinicalTrials","ids":["NCT00536835"]}],"maxPhaseForIndication":1}],"approvedIndications":[],"indicationCount":1}
{"id":"CHEMBL4297801","indications":[{"disease":"Orphanet_324","efoName":"fabry disease","references":[{"source":"ClinicalTrials","ids":["NCT01678898","NCT01769001","NCT01981720","NCT02795676","NCT02921620","NCT03018730","NCT03180840","NCT03566017","NCT03614234"]}],"maxPhaseForIndication":3}],"approvedIndications":[],"indicationCount":1}
{"id":"CHEMBL3991065","indications":[{"disease":"MONDO_0005277","efoName":"migraine disorder","references":[{"source":"FDA","ids":["label/2021/215206Orig1s000lbl.pdf"]},{"source":"ClinicalTrials","ids":["NCT02848326","NCT03700320","NCT03777059","NCT03855137","NCT03939312","NCT04437433","NCT04686136","NCT04740827","NCT04818515","NCT04829747","NCT04961671"]}],"maxPhaseForIndication":4}],"approvedIndications":["MONDO_0005277"],"indicationCount":1}
